Workbook

Sheet Revision
A1: Date | B1: Revision | C1: Sheet
A2: 46122 | B2: Removed all N95 ITP Update J6412 & N97 ITP Update MeteorLake ITP | C2: Windows POS & BOX PC ITP
A3: 46122 | B3: Update m.2 3x4 128G ITP Add A/T/D base ITP Add adapter ITP | C3: Optionals
A4: 46122 | B4: Add A&E/G/Audrey-2/J14/C/Alfa peripheral ITP Add M10 ITP Add License ITP Add A5 & A7 KDS kit ITP Add PS-103 & PS-107 ITP Add External IO Box ITP Add Payment Brackets (PTU only) ITP Add IoT (Partner Brand) ITP | C4: A E Series Peripherals G Series Peripherals Audrey-2 Peripherals J14 Peripherals C Series Peripherals BOX PC Alfa Peripherals License M10 KDS A5 & A7 Steam Proof PS-103.107 Stand External IO Box Payment Brackets (PTU) IoT (Partner Brand)

Sheet Windows POS & Box PC ITP
A1: Date | B1: 46122
A3: Terminal | B3: Platform | C3: Size | D3: PCB Version | E3: DDR4 RAM | F3: DDR5 RAM | G3: Storage | H3: Adaptor | I3: Base | J3: CPU ITP | K3: RAM ITP | L3: SSD ITP | M3: ITP w/o RAM & SSD | N3: ITP | O3: Remark
A4: A4-1-AL | B4: i3-1215U | C4: 15* | E4: 4G | G4: 128G - 4*4 | H4: 90W | I4: A Base | K4: =Optionals!$E$3 -> 60 | L4: =Optionals!$E$11 -> 88 | M4: 500 | N4: =K4+L4+M4 -> 648
A5: A4-1-AL | B5: i3-1215UE | C5: 15* | E5: 4G | G5: 128G - 4*4 | H5: 90W | I5: A Base | K5: =Optionals!$E$3 -> 60 | L5: =Optionals!$E$11 -> 88 | M5: 710 | N5: 852
A6: A4-1-AL | B6: i5-1245U | C6: 15* | E6: 4G | G6: 128G - 4*4 | H6: 90W | I6: A Base | K6: =Optionals!$E$3 -> 60 | L6: =Optionals!$E$11 -> 88 | M6: =660+25 -> 685 | N6: =K6+L6+M6 -> 833
A7: A4-1-AL | B7: i5-1245UE | C7: 15* | E7: 4G | G7: 128G - 4*4 | H7: 90W | I7: A Base | K7: =Optionals!$E$3 -> 60 | L7: =Optionals!$E$11 -> 88 | M7: 745 | N7: 887
A8: A4-1-AL | B8: i7-1265U | C8: 15* | E8: 4G | G8: 128G - 4*4 | H8: 90W | I8: A Base | K8: =Optionals!$E$3 -> 60 | L8: =Optionals!$E$11 -> 88 | M8: =860+25 -> 885 | N8: =K8+L8+M8 -> 1033
A9: A4-1-AL | B9: i7-1265UE | C9: 15* | E9: 4G | G9: 128G - 4*4 | H9: 90W | I9: A Base | K9: =Optionals!$E$3 -> 60 | L9: =Optionals!$E$11 -> 88 | M9: 885 | N9: 1027
A10: A4-1-E | B10: J6412 | C10: 15* | E10: 4G | G10: 128G - 3*4 | H10: 65W | I10: A Base | K10: =Optionals!$E$3 -> 60 | L10: =Optionals!$E$15 -> 65 | M10: =400+30 -> 430 | N10: =K10+L10+M10 -> 555
A11: A4-2-E | B11: J6412 | C11: 15* | E11: 4G | G11: 128G - 3*4 | H11: 65W | I11: A Base | K11: =Optionals!$E$3 -> 60 | L11: =Optionals!$E$15 -> 65 | M11: =400+30 -> 430 | N11: =K11+L11+M11 -> 555
A12: A4-2-M | B12: 125U | C12: 15* | F12: 8G | G12: 128G - 4*4 | H12: 90W | I12: A Base | K12: =Optionals!$E$7 -> 165 | L12: =Optionals!$E$11 -> 88 | M12: 665 | N12: =K12+L12+M12 -> 918 | O12: *vPro Essential
A13: A4-2-M | B13: 135U | C13: 15* | F13: 8G | G13: 128G - 4*4 | H13: 90W | I13: A Base | K13: =Optionals!$E$7 -> 165 | L13: =Optionals!$E$11 -> 88 | M13: =665+60 -> 725 | N13: =K13+L13+M13 -> 978 | O13: *vPro Enterprise
A14: A4-2-M | B14: 155U | C14: 15* | F14: 8G | G14: 128G - 4*4 | H14: 90W | I14: A Base | K14: =Optionals!$E$7 -> 165 | L14: =Optionals!$E$11 -> 88 | M14: 915 | N14: =K14+L14+M14 -> 1168 | O14: *vPro Essential
A15: A4-2-M | B15: 165U | C15: 15* | F15: 8G | G15: 128G - 4*4 | H15: 90W | I15: A Base | K15: =Optionals!$E$7 -> 165 | L15: =Optionals!$E$11 -> 88 | M15: =915+30 -> 945 | N15: =K15+L15+M15 -> 1198 | O15: *vPro Enterprise
A16: A4-2-N | B16: N305 | C16: 15* | E16: 4G | G16: 128G - 3*4 | H16: 65W | I16: A Base | K16: =Optionals!$E$3 -> 60 | L16: =Optionals!$E$15 -> 65 | M16: =500+60 -> 560 | N16: =K16+L16+M16 -> 685 | O16: *By request, project base
A17: A4-2-N | B17: N97 | C17: 15* | E17: 4G | G17: 128G - 3*4 | H17: 65W | I17: A Base | K17: =Optionals!$E$3 -> 60 | L17: =Optionals!$E$15 -> 65 | M17: =415+60 -> 475 | N17: =K17+L17+M17 -> 600 | O17: *By request, project base
A18: A4-2-T | B18: i3-1115G4 | C18: 15* | E18: 4G | G18: 128G - 4*4 | H18: 65W | I18: A Base | K18: =Optionals!$E$3 -> 60 | L18: =Optionals!$E$11 -> 88 | M18: 500 | N18: =K18+L18+M18 -> 648
A19: A4-2-T | B19: i3-1115G4E | C19: 15* | E19: 4G | G19: 128G - 4*4 | H19: 65W | I19: A Base | K19: =Optionals!$E$3 -> 60 | L19: =Optionals!$E$11 -> 88 | M19: 710 | N19: 852
A20: A4-2-T | B20: i5-1145G7 | C20: 15* | E20: 4G | G20: 128G - 4*4 | H20: 65W | I20: A Base | K20: =Optionals!$E$3 -> 60 | L20: =Optionals!$E$11 -> 88 | M20: =660+25 -> 685 | N20: =K20+L20+M20 -> 833
A21: A4-2-T | B21: i5-1145G7E | C21: 15* | E21: 4G | G21: 128G - 4*4 | H21: 65W | I21: A Base | K21: =Optionals!$E$3 -> 60 | L21: =Optionals!$E$11 -> 88 | M21: 740 | N21: 882
A22: A4-2-T | B22: i7-1185G7 | C22: 15* | E22: 4G | G22: 128G - 4*4 | H22: 65W | I22: A Base | K22: =Optionals!$E$3 -> 60 | L22: =Optionals!$E$11 -> 88 | M22: =860+25 -> 885 | N22: =K22+L22+M22 -> 1033
A23: A4-2-T | B23: i7-1185G7E | C23: 15* | E23: 4G | G23: 128G - 4*4 | H23: 65W | I23: A Base | K23: =Optionals!$E$3 -> 60 | L23: =Optionals!$E$11 -> 88 | M23: 885 | N23: 1027
A24: A5-2-E | B24: J6412 | C24: 15.6" | E24: 4G | G24: 128G - 3*4 | H24: 65W | I24: A Base | K24: =Optionals!$E$3 -> 60 | L24: =Optionals!$E$15 -> 65 | M24: =410+30 -> 440 | N24: =K24+L24+M24 -> 565
A25: A5-2-M | B25: 125U | C25: 15.6" | F25: 8G | G25: 128G - 4*4 | H25: 90W | I25: A Base | K25: =Optionals!$E$7 -> 165 | L25: =Optionals!$E$11 -> 88 | M25: =665+10 -> 675 | N25: =K25+L25+M25 -> 928 | O25: *vPro Essential
A26: A5-2-M | B26: 135U | C26: 15.6" | F26: 8G | G26: 128G - 4*4 | H26: 90W | I26: A Base | K26: =Optionals!$E$7 -> 165 | L26: =Optionals!$E$11 -> 88 | M26: =675+60 -> 735 | N26: =K26+L26+M26 -> 988 | O26: *vPro Enterprise
A27: A5-2-M | B27: 155U | C27: 15.6" | F27: 8G | G27: 128G - 4*4 | H27: 90W | I27: A Base | K27: =Optionals!$E$7 -> 165 | L27: =Optionals!$E$11 -> 88 | M27: =915+10 -> 925 | N27: =K27+L27+M27 -> 1178 | O27: *vPro Essential
A28: A5-2-M | B28: 165U | C28: 15.6" | F28: 8G | G28: 128G - 4*4 | H28: 90W | I28: A Base | K28: =Optionals!$E$7 -> 165 | L28: =Optionals!$E$11 -> 88 | M28: =945+10 -> 955 | N28: =K28+L28+M28 -> 1208 | O28: *vPro Enterprise
A29: A5-2-N | B29: N305 | C29: 15.6" | E29: 4G | G29: 128G - 3*4 | H29: 65W | I29: A Base | K29: =Optionals!$E$3 -> 60 | L29: =Optionals!$E$15 -> 65 | M29: =560+10 -> 570 | N29: =K29+L29+M29 -> 695 | O29: *By request, project base
A30: A5-2-N | B30: N97 | C30: 15.6" | E30: 4G | G30: 128G - 3*4 | H30: 65W | I30: A Base | K30: =Optionals!$E$3 -> 60 | L30: =Optionals!$E$15 -> 65 | M30: =425+60 -> 485 | N30: =K30+L30+M30 -> 610 | O30: *By request, project base
A31: A5-2-T | B31: i3-1115G4 | C31: 15.6" | E31: 4G | G31: 128G - 4*4 | H31: 65W | I31: A Base | K31: =Optionals!$E$3 -> 60 | L31: =Optionals!$E$11 -> 88 | M31: =500+10 -> 510 | N31: =K31+L31+M31 -> 658
A32: A5-2-T | B32: i3-1115G4E | C32: 15.6" | E32: 4G | G32: 128G - 4*4 | H32: 65W | I32: A Base | K32: =Optionals!$E$3 -> 60 | L32: =Optionals!$E$11 -> 88 | M32: 720 | N32: 862
A33: A5-2-T | B33: i5-1145G7 | C33: 15.6" | E33: 4G | G33: 128G - 4*4 | H33: 65W | I33: A Base | K33: =Optionals!$E$3 -> 60 | L33: =Optionals!$E$11 -> 88 | M33: =685+10 -> 695 | N33: =K33+L33+M33 -> 843
A34: A5-2-T | B34: i5-1145G7E | C34: 15.6" | E34: 4G | G34: 128G - 4*4 | H34: 65W | I34: A Base | K34: =Optionals!$E$3 -> 60 | L34: =Optionals!$E$11 -> 88 | M34: 750 | N34: 892
A35: A5-2-T | B35: i7-1185G7 | C35: 15.6" | E35: 4G | G35: 128G - 4*4 | H35: 65W | I35: A Base | K35: =Optionals!$E$3 -> 60 | L35: =Optionals!$E$11 -> 88 | M35: =885+10 -> 895 | N35: =K35+L35+M35 -> 1043
A36: A5-2-T | B36: i7-1185G7E | C36: 15.6" | E36: 4G | G36: 128G - 4*4 | H36: 65W | I36: A Base | K36: =Optionals!$E$3 -> 60 | L36: =Optionals!$E$11 -> 88 | M36: 895 | N36: 1037
A37: A7-1-AL | B37: i3-1215U | C37: 21.5" | E37: 4G | G37: 128G - 4*4 | H37: 120W | I37: A Base | K37: =Optionals!$E$3 -> 60 | L37: =Optionals!$E$11 -> 88 | M37: =500+105 -> 605 | N37: =K37+L37+M37 -> 753
A38: A7-1-AL | B38: i3-1215UE | C38: 21.5" | E38: 4G | G38: 128G - 4*4 | H38: 120W | I38: A Base | K38: =Optionals!$E$3 -> 60 | L38: =Optionals!$E$11 -> 88 | M38: 815 | N38: 957
A39: A7-1-AL | B39: i5-1245U | C39: 21.5" | E39: 4G | G39: 128G - 4*4 | H39: 120W | I39: A Base | K39: =Optionals!$E$3 -> 60 | L39: =Optionals!$E$11 -> 88 | M39: =685+105 -> 790 | N39: =K39+L39+M39 -> 938
A40: A7-1-AL | B40: i5-1245UE | C40: 21.5" | E40: 4G | G40: 128G - 4*4 | H40: 120W | I40: A Base | K40: =Optionals!$E$3 -> 60 | L40: =Optionals!$E$11 -> 88 | M40: 850 | N40: 992
A41: A7-1-AL | B41: i7-1265U | C41: 21.5" | E41: 4G | G41: 128G - 4*4 | H41: 120W | I41: A Base | K41: =Optionals!$E$3 -> 60 | L41: =Optionals!$E$11 -> 88 | M41: =885+105 -> 990 | N41: =K41+L41+M41 -> 1138
A42: A7-1-AL | B42: i7-1265UE | C42: 21.5" | E42: 4G | G42: 128G - 4*4 | H42: 120W | I42: A Base | K42: =Optionals!$E$3 -> 60 | L42: =Optionals!$E$11 -> 88 | M42: 990 | N42: 1132
A43: A7-1-E | B43: J6412 | C43: 21.5" | E43: 4G | G43: 128G - 3*4 | H43: 90W | I43: A Base | K43: =Optionals!$E$3 -> 60 | L43: =Optionals!$E$15 -> 65 | M43: =510+30 -> 540 | N43: =K43+L43+M43 -> 665
A44: A7-2-E | B44: J6412 | C44: 21.5" | E44: 4G | G44: 128G - 3*4 | H44: 90W | I44: A Base | K44: =Optionals!$E$3 -> 60 | L44: =Optionals!$E$15 -> 65 | M44: =510+30 -> 540 | N44: =K44+L44+M44 -> 665
A45: A7-2-M | B45: 125U | C45: 21.5" | F45: 8G | G45: 128G - 4*4 | H45: 120W | I45: A Base | K45: =Optionals!$E$7 -> 165 | L45: =Optionals!$E$11 -> 88 | M45: =665+105 -> 770 | N45: =K45+L45+M45 -> 1023 | O45: *vPro Essential
A46: A7-2-M | B46: 135U | C46: 21.5" | F46: 8G | G46: 128G - 4*4 | H46: 120W | I46: A Base | K46: =Optionals!$E$7 -> 165 | L46: =Optionals!$E$11 -> 88 | M46: =725+105 -> 830 | N46: =K46+L46+M46 -> 1083 | O46: *vPro Enterprise
A47: A7-2-M | B47: 155U | C47: 21.5" | F47: 8G | G47: 128G - 4*4 | H47: 120W | I47: A Base | K47: =Optionals!$E$7 -> 165 | L47: =Optionals!$E$11 -> 88 | M47: =915+105 -> 1020 | N47: =K47+L47+M47 -> 1273 | O47: *vPro Essential
A48: A7-2-M | B48: 165U | C48: 21.5" | F48: 8G | G48: 128G - 4*4 | H48: 120W | I48: A Base | K48: =Optionals!$E$7 -> 165 | L48: =Optionals!$E$11 -> 88 | M48: =945+105 -> 1050 | N48: =K48+L48+M48 -> 1303 | O48: *vPro Enterprise
A49: A7-2-N | B49: N305 | C49: 21.5" | E49: 4G | G49: 128G - 3*4 | H49: 90W | I49: A Base | K49: =Optionals!$E$3 -> 60 | L49: =Optionals!$E$15 -> 65 | M49: =560+105 -> 665 | N49: =K49+L49+M49 -> 790 | O49: *By request, project base
A50: A7-2-N | B50: N97 | C50: 21.5" | E50: 4G | G50: 128G - 3*4 | H50: 90W | I50: A Base | K50: =Optionals!$E$3 -> 60 | L50: =Optionals!$E$15 -> 65 | M50: =525+60 -> 585 | N50: =K50+L50+M50 -> 710 | O50: *By request, project base
A51: A7-2-T | B51: i3-1115G4 | C51: 21.5" | E51: 4G | G51: 128G - 4*4 | H51: 120W | I51: A Base | K51: =Optionals!$E$3 -> 60 | L51: =Optionals!$E$11 -> 88 | M51: =500+105 -> 605 | N51: =K51+L51+M51 -> 753
A52: A7-2-T | B52: i3-1115G4E | C52: 21.5" | E52: 4G | G52: 128G - 4*4 | H52: 120W | I52: A Base | K52: =Optionals!$E$3 -> 60 | L52: =Optionals!$E$11 -> 88 | M52: 815 | N52: 957
A53: A7-2-T | B53: i5-1145G7 | C53: 21.5" | E53: 4G | G53: 128G - 4*4 | H53: 120W | I53: A Base | K53: =Optionals!$E$3 -> 60 | L53: =Optionals!$E$11 -> 88 | M53: =685+105 -> 790 | N53: =K53+L53+M53 -> 938
A54: A7-2-T | B54: i5-1145G7E | C54: 21.5" | E54: 4G | G54: 128G - 4*4 | H54: 120W | I54: A Base | K54: =Optionals!$E$3 -> 60 | L54: =Optionals!$E$11 -> 88 | M54: 845 | N54: 987
A55: A7-2-T | B55: i7-1185G7 | C55: 21.5" | E55: 4G | G55: 128G - 4*4 | H55: 120W | I55: A Base | K55: =Optionals!$E$3 -> 60 | L55: =Optionals!$E$11 -> 88 | M55: =885+105 -> 990 | N55: =K55+L55+M55 -> 1138
A56: A7-2-T | B56: i7-1185G7E | C56: 21.5" | E56: 4G | G56: 128G - 4*4 | H56: 120W | I56: A Base | K56: =Optionals!$E$3 -> 60 | L56: =Optionals!$E$11 -> 88 | M56: 990 | N56: 1132
A57: Alfa | B57: 125U | F57: 8G | G57: 128G - 4*4 | H57: 90W | I57: NA | K57: =Optionals!$E$7 -> 165 | L57: =Optionals!$E$11 -> 88 | M57: =510-20 -> 490 | N57: =K57+L57+M57 -> 743 | O57: *vPro Essential
A58: Alfa | B58: 135U | F58: 8G | G58: 128G - 4*4 | H58: 90W | I58: NA | K58: =Optionals!$E$7 -> 165 | L58: =Optionals!$E$11 -> 88 | M58: =490+60 -> 550 | N58: =K58+L58+M58 -> 803 | O58: *vPro Enterprise
A59: Alfa | B59: 155U | F59: 8G | G59: 128G - 4*4 | H59: 90W | I59: NA | K59: =Optionals!$E$7 -> 165 | L59: =Optionals!$E$11 -> 88 | M59: =710+30 -> 740 | N59: =K59+L59+M59 -> 993 | O59: *vPro Essential
A60: Alfa | B60: 165U | F60: 8G | G60: 128G - 4*4 | H60: 90W | I60: NA | K60: =Optionals!$E$7 -> 165 | L60: =Optionals!$E$11 -> 88 | M60: =740+30 -> 770 | N60: =K60+L60+M60 -> 1023 | O60: *vPro Enterprise
A61: Alfa | B61: i3-1115G4 | E61: 4G | G61: 128G - 4*4 | H61: 90W | I61: NA | K61: =Optionals!$E$3 -> 60 | L61: =Optionals!$E$11 -> 88 | M61: =210+115 -> 325 | N61: =K61+L61+M61 -> 473
A62: Alfa | B62: i3-1115G4E | E62: 4G | G62: 128G - 4*4 | H62: 90W | I62: NA | K62: =Optionals!$E$3 -> 60 | L62: =Optionals!$E$11 -> 88 | M62: 535 | N62: 677
A63: Alfa | B63: i5-1145G7 | E63: 4G | G63: 128G - 4*4 | H63: 90W | I63: NA | K63: =Optionals!$E$3 -> 60 | L63: =Optionals!$E$11 -> 88 | M63: =325+185 -> 510 | N63: =K63+L63+M63 -> 658
A64: Alfa | B64: i5-1145G7E | E64: 4G | G64: 128G - 4*4 | H64: 90W | I64: NA | K64: =Optionals!$E$3 -> 60 | L64: =Optionals!$E$11 -> 88 | M64: 565 | N64: 707
A65: Alfa | B65: i7-1185G7 | E65: 4G | G65: 128G - 4*4 | H65: 90W | I65: NA | K65: =Optionals!$E$3 -> 60 | L65: =Optionals!$E$11 -> 88 | M65: =510+200 -> 710 | N65: =K65+L65+M65 -> 858
A66: Alfa | B66: i7-1185G7E | E66: 4G | G66: 128G - 4*4 | H66: 90W | I66: NA | K66: =Optionals!$E$3 -> 60 | L66: =Optionals!$E$11 -> 88 | M66: 710 | N66: 852
A67: Alfa | B67: J6412 | E67: 4G | G67: 128G - 3*4 | H67: 65W | I67: NA | K67: =Optionals!$E$3 -> 60 | L67: =Optionals!$E$15 -> 65 | M67: =210+40 -> 250 | N67: =K67+L67+M67 -> 375
A68: Alfa | B68: N305 | E68: 4G | G68: 128G - 3*4 | H68: 65W | I68: NA | K68: =Optionals!$E$3 -> 60 | L68: =Optionals!$E$15 -> 65 | M68: 394 | N68: =K68+L68+M68 -> 519
A69: Alfa | B69: N97 | E69: 4G | G69: 128G - 3*4 | H69: 65W | I69: NA | K69: =Optionals!$E$3 -> 60 | L69: =Optionals!$E$15 -> 65 | M69: =230+60 -> 290 | N69: =K69+L69+M69 -> 415
A70: Alfa-MAX | B70: i3-12100TE - H610 | D70: H610 | E70: 4G | G70: 128G - 4*4 | H70: 120W | I70: NA | K70: =Optionals!$E$3 -> 60 | L70: =Optionals!$E$11 -> 88 | M70: 460 | N70: =SUBTOTAL(9,K70:M70) -> 608 | O70: *By request, project base, MOQ 100pcs
A71: Alfa-MAX | B71: i3-12100T - H610 | D71: H610 | E71: 4G | G71: 128G - 4*4 | H71: 120W | I71: NA | K71: =Optionals!$E$3 -> 60 | L71: =Optionals!$E$11 -> 88 | M71: 460 | N71: =SUBTOTAL(9,K71:M71) -> 608 | O71: *By request, project base, MOQ 100pcs
A72: Alfa-MAX | B72: i5-12500T - Q670 | D72: Q670 | E72: 4G | G72: 128G - 4*4 | H72: 120W | I72: NA | K72: =Optionals!$E$3 -> 60 | L72: =Optionals!$E$11 -> 88 | M72: =435+185 -> 620 | N72: =SUBTOTAL(9,K72:M72) -> 768 | O72: *By request, project base, MOQ 100pcs
A73: Alfa-MAX | B73: i5-12500TE - Q670 | D73: Q670 | E73: 4G | G73: 128G - 4*4 | H73: 120W | I73: NA | K73: =Optionals!$E$3 -> 60 | L73: =Optionals!$E$11 -> 88 | M73: 620 | N73: =SUBTOTAL(9,K73:M73) -> 768 | O73: *By request, project base, MOQ 100pcs
A74: Alfa-MAX | B74: i7-12700T - Q670 | D74: Q670 | E74: 4G | G74: 128G - 4*4 | H74: 120W | I74: NA | K74: =Optionals!$E$3 -> 60 | L74: =Optionals!$E$11 -> 88 | M74: =620+200 -> 820 | N74: =SUBTOTAL(9,K74:M74) -> 968 | O74: *By request, project base, MOQ 100pcs
A75: Alfa-MAX | B75: i7-12700TE - Q670 | D75: Q670 | E75: 4G | G75: 128G - 4*4 | H75: 120W | I75: NA | K75: =Optionals!$E$3 -> 60 | L75: =Optionals!$E$11 -> 88 | M75: 820 | N75: =SUBTOTAL(9,K75:M75) -> 968 | O75: *By request, project base, MOQ 100pcs
A76: Alfa-Mini | B76: 125U | F76: 8G | G76: 128G - 4*4 | H76: 90W | I76: NA | K76: =Optionals!$E$7 -> 165 | L76: =Optionals!$E$11 -> 88 | M76: 488 | N76: =K76+L76+M76 -> 741 | O76: *vPro Essential
A77: Alfa-Mini | B77: 135U | F77: 8G | G77: 128G - 4*4 | H77: 90W | I77: NA | K77: =Optionals!$E$7 -> 165 | L77: =Optionals!$E$11 -> 88 | M77: 548 | N77: =K77+L77+M77 -> 801 | O77: *vPro Enterprise
A78: Alfa-Mini | B78: 155U | F78: 8G | G78: 128G - 4*4 | H78: 90W | I78: NA | K78: =Optionals!$E$7 -> 165 | L78: =Optionals!$E$11 -> 88 | M78: 758 | N78: =K78+L78+M78 -> 1011 | O78: *vPro Essential
A79: Alfa-Mini | B79: 165U | F79: 8G | G79: 128G - 4*4 | H79: 90W | I79: NA | K79: =Optionals!$E$7 -> 165 | L79: =Optionals!$E$11 -> 88 | M79: 768 | N79: =K79+L79+M79 -> 1021 | O79: *vPro Enterprise
A80: Alfa-Mini | B80: i3-1115G4 | E80: 4G | G80: 128G - 4*4 | H80: 90W | I80: NA | K80: =Optionals!$E$3 -> 60 | L80: =Optionals!$E$11 -> 88 | M80: =200+115 -> 315 | N80: =K80+L80+M80 -> 463
A81: Alfa-Mini | B81: i3-1115G4E | E81: 4G | G81: 128G - 4*4 | H81: 90W | I81: NA | K81: =Optionals!$E$3 -> 60 | L81: =Optionals!$E$11 -> 88 | M81: 535 | N81: 677
A82: Alfa-Mini | B82: i5-1145G7 | E82: 4G | G82: 128G - 4*4 | H82: 90W | I82: NA | K82: =Optionals!$E$3 -> 60 | L82: =Optionals!$E$11 -> 88 | M82: =315+185 -> 500 | N82: =K82+L82+M82 -> 648
A83: Alfa-Mini | B83: i5-1145G7E | E83: 4G | G83: 128G - 4*4 | H83: 90W | I83: NA | K83: =Optionals!$E$3 -> 60 | L83: =Optionals!$E$11 -> 88 | M83: 555 | N83: 697
A84: Alfa-Mini | B84: i7-1185G7 | E84: 4G | G84: 128G - 4*4 | H84: 90W | I84: NA | K84: =Optionals!$E$3 -> 60 | L84: =Optionals!$E$11 -> 88 | M84: =500+200 -> 700 | N84: =K84+L84+M84 -> 848
A85: Alfa-Mini | B85: i7-1185G7E | E85: 4G | G85: 128G - 4*4 | H85: 90W | I85: NA | K85: =Optionals!$E$3 -> 60 | L85: =Optionals!$E$11 -> 88 | M85: 700 | N85: 842
A86: Alfa-Mini | B86: J6412 | E86: 4G | G86: 128G - 3*4 | H86: 65W | I86: NA | K86: =Optionals!$E$3 -> 60 | L86: =Optionals!$E$15 -> 65 | M86: =200+30 -> 230 | N86: =K86+L86+M86 -> 355
A87: Alfa-Mini | B87: N305 | E87: 4G | G87: 128G - 3*4 | H87: 65W | I87: NA | K87: =Optionals!$E$3 -> 60 | L87: =Optionals!$E$15 -> 65 | M87: 383 | N87: =K87+L87+M87 -> 508
A88: Alfa-Mini | B88: N97 | E88: 4G | G88: 128G - 3*4 | H88: 65W | I88: NA | K88: =Optionals!$E$3 -> 60 | L88: =Optionals!$E$15 -> 65 | M88: =220+60 -> 280 | N88: =K88+L88+M88 -> 405
A89: Alfa-Pro | B89: 125U | F89: 8G | G89: 128G - 4*4 | H89: 180W | I89: NA | K89: =Optionals!$E$7 -> 165 | L89: =Optionals!$E$11 -> 88 | M89: 563 | N89: =K89+L89+M89 -> 816 | O89: *vPro Essential
A90: Alfa-Pro | B90: 135U | F90: 8G | G90: 128G - 4*4 | H90: 180W | I90: NA | K90: =Optionals!$E$7 -> 165 | L90: =Optionals!$E$11 -> 88 | M90: 623 | N90: =K90+L90+M90 -> 876 | O90: *vPro Enterprise
A91: Alfa-Pro | B91: 155U | F91: 8G | G91: 128G - 4*4 | H91: 180W | I91: NA | K91: =Optionals!$E$7 -> 165 | L91: =Optionals!$E$11 -> 88 | M91: 833 | N91: =K91+L91+M91 -> 1086 | O91: *vPro Essential
A92: Alfa-Pro | B92: 165U | F92: 8G | G92: 128G - 4*4 | H92: 180W | I92: NA | K92: =Optionals!$E$7 -> 165 | L92: =Optionals!$E$11 -> 88 | M92: 843 | N92: =K92+L92+M92 -> 1096 | O92: *vPro Enterprise
A93: Alfa-Pro | B93: i3-1115G4 | E93: 4G | G93: 128G - 4*4 | H93: 180W | I93: NA | K93: =Optionals!$E$3 -> 60 | L93: =Optionals!$E$11 -> 88 | M93: =270+115 -> 385 | N93: =K93+L93+M93 -> 533
A94: Alfa-Pro | B94: i3-1115G4E | E94: 4G | G94: 128G - 4*4 | H94: 180W | I94: NA | K94: =Optionals!$E$3 -> 60 | L94: =Optionals!$E$11 -> 88 | M94: 595 | N94: 737
A95: Alfa-Pro | B95: i5-1145G7 | E95: 4G | G95: 128G - 4*4 | H95: 180W | I95: NA | K95: =Optionals!$E$3 -> 60 | L95: =Optionals!$E$11 -> 88 | M95: =385+185 -> 570 | N95: =K95+L95+M95 -> 718
A96: Alfa-Pro | B96: i5-1145G7E | E96: 4G | G96: 128G - 4*4 | H96: 180W | I96: NA | K96: =Optionals!$E$3 -> 60 | L96: =Optionals!$E$11 -> 88 | M96: 625 | N96: 767
A97: Alfa-Pro | B97: i7-1185G7 | E97: 4G | G97: 128G - 4*4 | H97: 180W | I97: NA | K97: =Optionals!$E$3 -> 60 | L97: =Optionals!$E$11 -> 88 | M97: =570+200 -> 770 | N97: =K97+L97+M97 -> 918
A98: Alfa-Pro | B98: i7-1185G7E | E98: 4G | G98: 128G - 4*4 | H98: 180W | I98: NA | K98: =Optionals!$E$3 -> 60 | L98: =Optionals!$E$11 -> 88 | M98: 770 | N98: 912
A99: Alfa-Pro | B99: J6412 | E99: 4G | G99: 128G - 3*4 | H99: 180W | I99: NA | K99: =Optionals!$E$3 -> 60 | L99: =Optionals!$E$15 -> 65 | M99: =270+30 -> 300 | N99: =K99+L99+M99 -> 425
A100: Alfa-Pro | B100: N305 | E100: 4G | G100: 128G - 3*4 | H100: 180W | I100: NA | K100: =Optionals!$E$3 -> 60 | L100: =Optionals!$E$15 -> 65 | M100: 458 | N100: =K100+L100+M100 -> 583
A101: Alfa-Pro | B101: N97 | E101: 4G | G101: 128G - 3*4 | H101: 180W | I101: NA | K101: =Optionals!$E$3 -> 60 | L101: =Optionals!$E$15 -> 65 | M101: =290+60 -> 350 | N101: =K101+L101+M101 -> 475
...

Sheet Optionals
B2: Option | C2: Description | D2: Size | E2: ITP | F2: Remark | H2: Upgrades / Downgrades | I2: ITP or ITP adder | J2: Remark
B3: RAM | C3: DDR4 | D3: 4G | E3: 60 | F3: Valid till Apr/E 2026 | H3: DDR4 4G upgrade to 8G | I3: =E4-E3 -> 40 | J3: Valid till Apr/E 2026
B4: RAM | C4: DDR4 | D4: 8G | E4: 100 | F4: Valid till Apr/E 2026 | H4: DDR4 8G upgrade to 16G | I4: =E5-E4 -> 100 | J4: Limited Supply
B5: RAM | C5: DDR4 | D5: 16G | E5: 200 | F5: Limited Supply | H5: GEN 3*4 128G upgrade to 256G | I5: =E16-E15 -> 30 | J5: Valid till Apr/E 2026
B6: RAM | C6: DDR4 | D6: 32G | E6: na | H6: GEN 4*4 128G upgrade to 256G | I6: =E12-E11 -> 30 | J6: Valid till Apr/E 2026
B7: RAM | C7: DDR5 | D7: 8G | E7: 165 | F7: Valid till Apr/E 2026 | H7: GEN 4*4 256G upgrade to 512G | I7: =E13-E12 -> 50 | J7: Valid till Apr/E 2026
B8: RAM | C8: DDR5 | D8: 16G | E8: na | H8: A base | I8: 35 | J8: A base in industrial packing (4pcs in one carton), MOQ 4pcs
B9: RAM | C9: DDR5 | D9: 32G | E9: na | H9: T base | I9: 24 | J9: T base in industrial packing (6pcs in one carton), MOQ 6pcs
B10: RAM | C10: DDR5 | D10: 48G | E10: na | H10: D base | I10: 27 | J10: D base in industrial packing (5pcs in one carton), MOQ 5pcs
B11: Storage | C11: m.2 GEN 4*4 | D11: 128G | E11: =82+6 -> 88 | F11: Valid till Apr/E 2026 | H11: T base upgrade to D base | I11: 3
B12: Storage | C12: m.2 GEN 4*4 | D12: 256G | E12: =E11+30 -> 118 | F12: Valid till Apr/E 2026 | H12: T base upgrade to A base | I12: 11
B13: Storage | C13: m.2 GEN 4*4 | D13: 512G | E13: =E12+50 -> 168 | F13: Valid till Apr/E 2026 | H13: Remove T base | I13: -24
B14: Storage | C14: m.2 GEN 4*4 | D14: 1TB | E14: na | H14: Remove A base | I14: -35
B15: Storage | C15: m.2 GEN 3*4 | D15: 128G | E15: 65 | F15: Valid till Apr/E 2026 | H15: A base to D base | I15: =27-35 -> -8
B16: Storage | C16: m.2 GEN 3*4 | D16: 256G | E16: 95 | F16: Valid till Apr/E 2026 | H16: A base to T base | I16: =24-35 -> -11
B17: Storage | C17: m.2 GEN 3*4 | D17: 512G | E17: na | H17: Brown Carton to Color Carton | I17: 2
B18: Storage | C18: m.2 GEN 3*4 | D18: 1TB | E18: na | H18: Anti-Glare -- A4 only | I18: 10
H19: 60W Adapter | I19: 16
H20: 90W Adapter | I20: 24
H21: 120W Adapter | I21: 32
H22: 180W Adapter | I22: 44
H23: 65W to 90W | I23: 8
H24: 90W to 120W | I24: 8
H25: 65W to 180W | I25: 28
H26: 90W to 180W | I26: 20
H27: 120W to 180W | I27: 12

Sheet A E Series Peripherals
A1: Date: | B1: NEW
B2: A5/E5/A4/A7 10.1" 2nd Display (A5 needs AR-100 separately, E5 needs ER-100 separately, A4 needs AR-104, A7 needs AR-107 separately) | D2: ITP | E2: Remark
B3: 2614551101302 | C3: CD-101C+JST Cable Only/9cm/PTU/NO Logo/Silver/1.1/GP | D3: =93.125+5+15 -> 113.125
B4: 2614151101313 | C4: CD-101C+JST Cable Only/9cm/NO Logo/Black/1.1/G+ | D4: =88.75+5+15 -> 108.75
B5: 2614551101304 | C5: CD-101C+JST Cable Only/PCT/9cm/PTU/NO Logo/Silver/1.1/GP | D5: =118.125+5+15 -> 138.125
B6: 2614151101314 | C6: CD-101C+JST Cable Only/PCT/9cm/NO Logo/Black/1.1/G+ | D6: =113.75+5+15 -> 133.75
B7: 2614151101315 | C7: CD-101C+JST Cable Only/9cm/NO Logo/White+Silver/1.1/G+ | D7: 113 | E7: White+Silver
B8: 2614151101317 | C8: CD-101C+JST Cable Only/9cm/Partner Logo/Black/1.1/G+ | D8: 109 | E8: W/Partner logo
B9: 2614151101318 | C9: CD-101C+JST Cable Only/PCT/9cm/Partner Logo/Black/1.1/G+ | D9: =113.75+5+15 -> 133.75 | E9: W/Partner logo
B10: 1721217210031 | C10: Cable/JST4P(wire-wire)(2.0)+USB-A/150cm/CD-101C/G+ | D10: 2 | E10: Conversion to USB Type A head for CD-101C with 150cm cable length, so can be used to all POSs with USB Type A port
B11: 1721217210032 | C11: Cable/JST4P(wire-wire)(2.0)+USB-A/72cm/CD-101C/G+ | D11: 2 | E11: Conversion to USB Type A head for CD-101C with 72cm cable length, so can be used to all POSs with USB Type A port
B12: E5 Peripherals
B13: 790500SB91100 | C13: MSR Module/ID123/E5-1/Black/GP | D13: 30 | E13: MSR only
B14: 790500SB91701 | C14: Multi Reader/ID123+RFID(MD-550V+)/E5-1/Black/GP | D14: 80 | E14: MSR+RFID
B15: 790500SB91800 | C15: Multi Reader/ID123+IC Card/E5-1/Black/GP | D15: 80 | E15: MSR+EMV certified IC card
B16: 790500SB91A00 | C16: Multi Reader/ID123+iButton/E5-1/Black/GP | D16: 65 | E16: MSR+iButton (Non-Magnetic)
B17: 790500SB91A10 | C17: Multi Reader/ID123+iButton(Magnetic Probe)/E5-1/Black/GP | D17: 75 | E17: MSR+iButton (Magnetic)
B18: 790500SB91B00 | C18: Multi Reader/ID123+RFID+IC Card/E5-1/Black/GP | D18: 126 | E18: MSR+RFID+EMV certified IC card
B19: 790500SB91900 | C19: Multi Reader/ID123+Fingerprint/E5-1/Black/GP | D19: 105 | E19: MSR+Fingerprint
B20: 790500SB91C00 | C20: Multi Reader/ID123+Fingerprint+IC Card/E5-1/Black/GP | D20: 151 | E20: MSR+Fingerprint+EMV certified IC Card
B21: 790500SB91E01 | C21: Multi Reader/ID123+Fingerprint+RFID on Side(RF-551V)/E5-1/Black/GP | D21: 140 | E21: MSR + Fingerprint+RFID
B22: By Request | C22: E5 Fingerprint (Multi Reader) | D22: 90
B23: 790B500SB0000 | C23: VFD Module/CD7220/BOE/12V/E5-1/Black C/GP | D23: 45 | E23: VFD
B24: 790500SB92200 | C24: Additional 2 x COM Port | D24: 5
B25: 790500SB92300 | C25: Additional 1 x COM + 1 x LPT Port | D25: 5 | E25: *Only available for Kabylake and Skylake
B26: 790500SB92100 | C26: Additional 1 x COM + 2 x USB 3.0/2.0 | D26: 20
B27: 790500SB92400 | C27: Additional 2 x USB3.0/2.0 + 1 x 12V & 1 x 24V Powered USB (This spec will use the internal USB port reserved for CD-101C. If your customer really need both working, the maintenance USB port at the side of E5 needs to be removed.) | D27: 50 | E27: Must apply with 180W adapter *Only available for Kabylake and Skylake
B28: By Request | C28: Additional 2 x USB2.0 + 1 x 12V & 1 x 24V Powered USB | D28: 50 | E28: Must apply with 180W adapter *Only available for Alder lake (E5-1-AL)
B29: NA | C29: Additional LAN for E5 (SG project) | D29: 1pcs: 98 5pcs 26 30pcs 20 50pcs 20 | E29: Built-in directly into FG
B30: 790500SB92500 | C30: Additional LAN for E5 (SG project) | D30: 1pcs: 105 5pcs 30 30pcs 24 50pcs 24 | E30: Purchase seperately (790 with packing)
C31: Upgrade from 90W to 180W | D31: 20
B32: 7900ER1000000 | C32: ER-100/Black/GP ER-100 hinge | D32: 15 | E32: For CD-70, CD-101C bracket for E5 only
B33: 79050A5199103 | C33: Wifi+BT Kit/6E AX210/GP(E5/Ax/Gx-K/A/B/E/T/AL,BW-xxx-W,C1x-E) | D33: 25 | E33: WIFI 6E, J1900/ J3455/ Kabylake/ Skylake/ Elkhart Lake/ Alder Lake/ N97 & N305 (with M.2 to PCIe board)
B34: 79050A5199104 | C34: Wifi+BT Kit/6E AX210/Ax-E,AL,T,C10-1E/GP(W/O M.2-PCIE) | D34: 25 | E34: WIFI 6, Alder Lake / Elkhart Lake/ TigerLake/ N97 & N305 only support WIFI 6E (W/O M.2 to PCIe board)
B35: 79050A5199100 | C35: Wifi Antenna Kit/A5,E5/GP (Antenna only) | D35: 15 | E35: For A5/A4/E5/A7/G4/G5/BW-215 (Antenna only)
B36: 77050A5199200 | C36: Assy/Camera Kit/5M/A5,E5/GP | D36: 35 | E36: For A5/E5 embedded only, Factory Option (not for AG Panel) MOQ TBC
B37: 790500SB99100 | C37: E5+Power adaptor/RP-700 mounting bracket RP-700+Adaptor Bracket Kit for Wall Mount/E5-1/Black | D37: MOQ 2pcs: $185 MOQ 64pcs: $88 MOQ 96pcs: $76 MOQ 192pcs: $65 | E37: *PPR 1160 for CCL
B38: A5 Peripherals
B39: 79050A5191100 | C39: MSR Module/ID123/A5-1/Black/GP | D39: 30 | E39: MSR only Black
B40: 79050A5191105 | C40: MSR Module/ID123(Beep)A5-1-E,AL/Black/GP | D40: 30 | E40: MSR only Black MSR Beep default disabled
B41: 79050A5191101 | C41: MSR Module/ID123/A5-1/Silver/GP | D41: 30 | E41: MSR only Silver
B42: 79050A5191700 | C42: Multi Reader/ID123+RFID(MD-550L+)/A5-1/Black/GP | D42: 80 | E42: MSR+RFID Black
B43: 79050A5191701 | C43: Multi Reader/ID123+RFID(MD-550L+)/A5-1/Silver/GP | D43: 80 | E43: MSR+RFID Silver
B44: 79050A5191704 | C44: Multi Reader/ID123+RFID on Side(RF-551V)/A5-1/Black/GP | D44: 80 | E44: MSR+RFID on Side Black
B45: 79050A5191705 | C45: Multi Reader/ID123+RFID on Side(RF-551V)/A5-1/PTAU/Black/GP | D45: 80 | E45: MSR+RFID on Side Black PTAU only
B46: 79050A5191800 | C46: Multi Reader/ID123+EMV IC Card/A5-1/Black/GP | D46: 80 | E46: MSR+EMV certified IC card Black, please check MOQ when order
B47: 79050A5191900 | C47: Multi Reader/ID123+Fingerprint/A5-1/Black/GP | D47: 105 | E47: MSR+Fingerprint Black
B48: 79050A5191A00 | C48: Multi Reader/ID123+iButton/A5-1/Black/GP | D48: 65 | E48: MSR+iButton Black (Non-Magnetic)
B49: 79050A5191A10 | C49: Multi Reader/ID123+iButton(Magnetic Probe)/A5-1/Black/GP | D49: 75 | E49: MSR+iButton Black (Magnetic)
B50: 79050A5191B00 | C50: Multi Reader/ID123+RFID+EMV IC Card/A5-1/Black/GP | D50: 126 | E50: MSR+RFID+EMV certified IC card Black
... B59: 7900AS1000000 | C59: AS-100/Black/GP AS-100 hinge | D59: 18 | E59: VESA 75x75 2nd display bracket for A series
B60: 7905000000025 | C60: VESA Bracket Kit/100-75/M4 Screw/Black | D60: MOQ 1pcs: $80 MOQ 20pcs: $10 MOQ 50pcs: $8 | E60: A Stand VESA Wall Mount 75 convert to 100 bracket Connect to AS-100
B61: 79050A5199103 | C61: Wifi+BT Kit/6E AX210/GP(E5/Ax/Gx-K/A/B/E/T/AL,BW-xxx-W,C1x-E) | D61: 25 | E61: WIFI 6E, J1900/ J3455/ Kabylake/ Skylake/ Elkhart Lake/ Alder Lake/ N97 & N305 (with M.2 to PCIe board)
B62: 79050A5199104 | C62: Wifi+BT Kit/6E AX210/Ax-E,AL,T,C10-1E/GP(W/O M.2-PCIE) | D62: 25 | E62: WIFI 6, Alder Lake / Elkhart Lake/ TigerLake/ N97 & N305 only support WIFI 6E (W/O M.2 to PCIe board)
B63: 79050A5199100 | C63: Wifi Antenna Kit/A5,E5/GP (Antenna only) | D63: 15 | E63: For A5/A4/E5/A7/G4/G5/BW-215 (Antenna only)
B64: 79050A5103001 | C64: Base Kit/A5-1/BC/B+G/Partner Logo/GP | D64: 46 | E64: A series stand with A5 POS Terminal Packing
B65: 79050A5199400 | C65: A5 KDS kit (A5 not included & no water proof) KDS Kit(No waterproof)/A5/Black | D65: MOQ 1pc = $270 MOQ 5pc = $135 MOQ 10pc = $130 MOQ 25pc = $125 | E65: Recommend applying KDS Kit with A5 finished product when manufacturing
C66: A5 KDS sealing applied | D66: 5
B67: A5 2D Scanner and Camera when position as Landscape mode (must purchase Side Kit + Scanner/Camera)
B68: 79050A5199000 | C68: SCN-300,CAMERA-300 on Side Kit/A5/Black/GP (MOQ 10pcs) | D68: 25 | E68: Side Kit to install SCN-300 or CAMERA-300 at the Right-hand of Screen (need to purchase SCN-300 or CAMERA-300 separately)
B69: 79050A7199216 | C69: SCN-300/2D(N4680)/A4,A7,G4,G5/1.1/B+G | D69: 115 | E69: 2D Scanner - install at the Top / Right-hand of Screen
B70: 79050A7199325 | C70: CAMERA-300/8M/AV5180A1D/A4,A7,G4,G5/1.1/B+G/GP | D70: 55 | E70: Camera - install at the Top / Right-hand of Screen
B71: 77050A5199200 | C71: Assy/Camera Kit/5M/A5,E5/GP | D71: 35 | E71: For A5/E5 embedded only, Factory Option (not for AG Panel) MOQ TBC
B72: A4 Peripherals
B73: 79050A4191105 | C73: MSR Module/ID123/A4-1/1.1/Black/GP | D73: 30 | E73: MSR only Black
B74: 79050A4191107 | C74: MSR Module/ID123(Beep)/A4-1/1.1/Black/GP | D74: 30 | E74: MSR only Black MSR Beep default disabled
B75: 79050A4191106 | C75: MSR Module/ID123/A4-1/1.1/Silver/GP | D75: 30 | E75: MSR only Silver
B76: 79050A4191700 | C76: Multi Reader/ID123+RFID(MD-550L+)/A4-1/Black/GP | D76: 80 | E76: MSR+RFID Black
B77: 79050A4191701 | C77: Multi Reader/ID123+RFID(MD-550L+)/A4-1/Silver/GP | D77: 80 | E77: MSR+RFID Silver
B78: 79050A4191703 | C78: Multi Reader/ID123+RFID on Side(RF-551V)/A4-1/Black/GP | D78: 80 | E78: MSR+RFID on Side Black
B79: 79050A4191704 | C79: Multi Reader/ID123+RFID on Side(RF-551V)/A4-1/PTAU/Black/GP | D79: 80 | E79: MSR+RFID on Side Black PTAU only
B80: 79050A4191800 | C80: Multi Reader/ID123+EMV IC Card/A4-1/Black/GP | D80: 80 | E80: MSR+EMV certified IC card Black, please check MOQ when order
B81: 79050A4191801 | C81: Multi Reader/ID123+EMV IC Card/A4-1/Silver/GP | D81: 80 | E81: MSR+EMV certified IC card Black, please check MOQ when order
B82: 79050A4191900 | C82: Multi Reader/ID123+Fingerprint/A4-1/Black/GP | D82: 105 | E82: MSR+Fingerprint Black
B83: 79050A4191901 | C83: Multi Reader/ID123+Fingerprint/A4-1/Silver/GP | D83: 105 | E83: MSR+Fingerprint Silver
B84: 79050A4191A00 | C84: Multi Reader/ID123+iButton/A4-1/Black/GP | D84: 65 | E84: MSR+iButton Black (Non-Magnetic)
... B91: 79050A4191C01 | C91: Multi Reader/ID123+Fingerprint+EMV IC Card/A4-1/Silver/GP | D91: 151 | E91: MSR+Fingerprint+EMV certified IC Card Silver
B92: 79050A4191400 | C92: Multi Reader/RFID(MD-550L+)/A4-1/Black/GP | D92: 55
B93: 79050A7191301 | C93: BIO Module/Fingerprint/A4,A7,G4,G5,AD215/Black/GP | D93: 90
B94: 790B50A410000 | C94: VFD Module/CD7220/BOE/12V/A4-1/Black/GP | D94: 45 | E94: VFD Black
B95: 790B50A410001 | C95: VFD Module/CD7220/BOE/12V/A4-1/Silver/GP | D95: 45 | E95: VFD Silver
B96: 7900AR1040000 | C96: AR-104/Black/GP AR-104 Hinge | D96: 15 | E96: For CD-70, CD-101C bracket for A4 only
B97: 7900AR1040100 | C97: AR-104 Plus/Black/GP (Strength Enhancement edition) | D97: 20 | E97: VFD Cover with Strength Enhancement for PTU For CD-70, CD-101C bracket for A5 only
B98: 7900AR1040001 | C98: AR-104/Silver/GP AR-104 Hinge | D98: 15 | E98: For CD-70, CD-101C bracket for A4 only
B99: 7900AS1000000 | C99: AS-100/Black/GP AS-100 hinge | D99: 18 | E99: VESA 75x75 2nd display bracket for A series
B100: 7905000000025 | C100: VESA Bracket Kit/100-75/M4 Screw/Black | D100: MOQ 1pcs: $80 MOQ 20pcs: $10 MOQ 50pcs: $8 | E100: A Stand VESA Wall Mount 75 convert to 100 bracket Connect to AS-100
B101: 79050A5199103 | C101: Wifi+BT Kit/6E AX210/GP(E5/Ax/Gx-K/A/B/E/T/AL,BW-xxx-W,C1x-E) | D101: 25 | E101: WIFI 6E, J1900/ J3455/ Kabylake/ Skylake/ Elkhart Lake/ Alder Lake/ N97 & N305 (with M.2 to PCIe board)
B102: 79050A5199104 | C102: Wifi+BT Kit/6E AX210/Ax-E,AL,T,C10-1E/GP(W/O M.2-PCIE) | D102: 25 | E102: WIFI 6, Alder Lake / Elkhart Lake/ TigerLake/ N97 & N305 only support WIFI 6E (W/O M.2 to PCIe board)
B103: 79050A5199100 | C103: Wifi Antenna Kit/A5,E5/GP | D103: 15 | E103: For A5/A4/E5/A7/G4/G5/BW-215 (Antenna only)
B104: A4 2D Scanner and Camera when position as Landscape mode
B105: 79050A7199216 | C105: SCN-300/2D(N4680)/A4,A7,G4,G5/1.1/B+G | D105: 115 | E105: 2D Scanner - install at the Top / Right-hand of Screen
B106: 79050A7199325 | C106: CAMERA-300/8M/AV5180A1D/A4,A7,G4,G5/1.1/B+G/GP | D106: 55 | E106: Camera - install at the Top / Right-hand of Screen
B107: A7 Peripherals
B108: 79050A7191100 | C108: MSR Module/ID123/A7-1/Black/GP | D108: 30 | E108: MSR only Black
B109: 79050A7191102 | C109: MSR Module/ID123(Beep)/A7-1-E,AL/Black/GP | D109: 30 | E109: MSR only Black MSR Beep default disabled
B110: 79050A7191101 | C110: MSR Module/ID123/A7-1/Silver/GP | D110: 30 | E110: MSR only Silver
B111: 79050A7191700 | C111: Multi Reader/ID123+RFID(MD-550L+)/A7-1/Black/GP | D111: 80 | E111: MSR+RFID Black
B112: 79050A7191701 | C112: Multi Reader/ID123+RFID(MD-550L+)/A7-1/Silver/GP | D112: 80 | E112: MSR+RFID Silver
B113: 79050A7191800 | C113: Multi Reader/ID123+EMV IC Card/A7-1/Black/GP | D113: 80 | E113: MSR+EMV certified IC card Black
B114: 79050A7191801 | C114: Multi Reader/ID123+EMV IC Card/A7-1/Silver/GP | D114: 80 | E114: MSR+EMV certified IC card Silver
...

Sheet G Series Peripherals
A1: Date: | B1: New
B2: G Series 10.1" 2nd Display (G4 needs GR-104, G5 needs GR-100 separately) | D2: ITP | E2: Remark
B3: 2614151101313 | C3: CD-101C+JST Cable Only/9cm/NO Logo/Black/1.1/G+ | D3: =88.75+5+15 -> 108.75 | G3: =350+10+24+17 -> 401
B4: 2614151101314 | C4: CD-101C+JST Cable Only/PCT/9cm/NO Logo/Black/1.1/G+ | D4: =113.75+5+15 -> 133.75
B5: 2614151101317 | C5: CD-101C+JST Cable Only/9cm/Partner Logo/Black/1.1/G+ | D5: 109 | E5: W/Partner logo
B6: 2614151101318 | C6: CD-101C+JST Cable Only/PCT/9cm/Partner Logo/Black/1.1/G+ | D6: =113.75+5+15 -> 133.75 | E6: W/Partner logo
B7: 1721217210031 | C7: Cable/JST4P(wire-wire)(2.0)+USB-A/150cm/CD-101C/G+ | D7: 2 | E7: Conversion to USB Type A head for CD-101C with 150cm cable length, so can be used to all POSs with USB Type A port
B8: 1721217210032 | C8: Cable/JST4P(wire-wire)(2.0)+USB-A/72cm/CD-101C/G+ | D8: 2 | E8: Conversion to USB Type A head for CD-101C with 72cm cable length, so can be used to all POSs with USB Type A port
B9: G5 Peripherals
B10: 79050G4191100 | C10: MSR Module/ID123/G4-1,G5-1/Black/GP | D10: 30 | E10: MSR only
B11: 79050G4191101 | C11: MSR Module/ID123(Beep)/G4-1,G5-1/Black/GP | D11: 30 | E11: MSR only Black MSR Beep default disabled
B12: 79050G4191900 | C12: Multi Reader/ID123+Fingerprint/G4-1,G5-1/Black/GP | D12: 105 | E12: MSR+Fingerprint
B13: 790B50G510000 | C13: VFD Module/CD7220/BOE/12V/G5-1/Black/GP | D13: 45 | E13: VFD
B14: 79050G4191400 | C14: Multi Reader/RFID(MD-550L+)/G4-1,G5-1/Black/GP | D14: 55 | E14: RFID Only
B15: 79050G4191700 | C15: MSR+RFID Multi Reader/ID123+RFID(MD-550L+)/G4-1,G5-1/Black/GP | D15: 80 | E15: By Request to apply P/N
B16: 79050G4191800 | C16: Multi Reader/ID123+EMV IC Card/G4-1,G5-1/Black/GP | D16: 80 | E16: By Request to apply P/N
B17: 79050G4191600 | C17: Multi Reader/iButton/G4-1,G5-1/Black/GP | D17: 50 | E17: iButton Black (Non-Magnetic)
B18: 79050G4191601 | C18: Multi Reader/iButton(Magnetic Probe)/G4-1,G5-1/Black/GP | D18: 60 | E18: iButton Black (Magnetic)
B19: By Request | C19: MSR+iButton | D19: 65 | E19: By Request to apply P/N
B20: 79050G4191A00 | C20: MSR+iButton(Magnetic Probe) Multi Reader/ID123+iButton(Magnetic Probe)/G4-1,G5-1/Black/GP | D20: 75 | E20: By Request to apply P/N
B21: By Request | C21: MSR+RFID+EMV IC Card | D21: 126 | E21: By Request to apply P/N
... B28: 7900GR1000000 | C28: GR-100/Black/GP | D28: 15 | E28: For CD-70, CD-101C bracket for G5 only (VFD position)
B29: G5 2D Scanner and Camera when position as Landscape mode
B30: 79050A7199216 | C30: SCN-300/2D(N4680)/A4,A7,G4,G5/1.1/B+G | D30: 115 | E30: 2D Scanner - install at the Top / Right / Left-hand side of Screen. Same as A series
B31: 79050A7199325 | C31: CAMERA-300/8M/AV5180A1D/A4,A7,G4,G5/1.1/B+G/GP | D31: 55 | E31: Camera - install at the Top / Right-hand of Screen
B32: G4 Peripherals
B33: 79050G4191100 | C33: MSR Module/ID123/G4-1,G5-1/Black/GP | D33: 30 | E33: MSR only
B34: 79050G4191101 | C34: MSR Module/ID123(Beep)/G4-1,G5-1/Black/GP | D34: 30 | E34: MSR only Black MSR Beep default disabled
B35: 79050G4191900 | C35: Multi Reader/ID123+Fingerprint/G4-1,G5-1/Black/GP | D35: 105 | E35: MSR+Fingerprint
B36: 790B50G410000 | C36: VFD Module/CD7220/BOE/12V/G4-1/Black/GP | D36: 45 | E36: VFD
B37: 79050G4191400 | C37: Multi Reader/RFID(MD-550L+)/G4-1,G5-1/Black/GP | D37: 55 | E37: RFID Only
B38: 79050G4191700 | C38: MSR+RFID Multi Reader/ID123+RFID(MD-550L+)/G4-1,G5-1/Black/GP | D38: 80 | E38: By Request to apply P/N
B39: 79050G4191800 | C39: Multi Reader/ID123+EMV IC Card/G4-1,G5-1/Black/GP | D39: 80
B40: By Request | C40: MSR+iButton | D40: 65 | E40: By Request to apply P/N
B41: 79050G4191A00 | C41: MSR+iButton(Magnetic Probe) Multi Reader/ID123+iButton(Magnetic Probe)/G4-1,G5-1/Black/GP | D41: 75 | E41: By Request to apply P/N
B42: By Request | C42: MSR+RFID+EMV IC Card | D42: 126 | E42: By Request to apply P/N
B43: 79050G4191C00 | C43: Multi Reader/ID123+Fingerprint+EMV IC Card/G4-1,G5-1/Black/GP | D43: 151 | E43: MSR+Fingerprint+EMV certified IC Card
B44: 79050A7191301 | C44: BIO Module/Fingerprint/A4,A7,G4,G5,AD215/Black/GP | D44: 90 | E44: Figerprinter only
B45: 79050A5199103 | C45: Wifi+BT Kit/6E AX210/GP(E5/Ax/Gx-K/A/B/E/T/AL,BW-xxx-W,C1x-E) | D45: 25 | E45: WIFI 6E, J1900/ J3455/ Kabylake/ Skylake/ Elkhart Lake/ Alder Lake/ N97 & N305 (with M.2 to PCIe board)
B46: 79050A5199104 | C46: Wifi+BT Kit/6E AX210/Ax-E,AL,T,C10-1E/GP(W/O M.2-PCIE) | D46: 25 | E46: WIFI 6, Alder Lake / Elkhart Lake/ TigerLake/ N97 & N305 only support WIFI 6E (W/O M.2 to PCIe board)
B47: 79050A5199100 | C47: Wifi Antenna Kit/A5,E5/GP | D47: 15 | E47: For A5/A4/E5/A7/G4/G5/BW-215 (Antenna only)
B48: 7900GS1010000 | C48: GS-101+DB-100/Black/GP | D48: 35 | E48: Required GS-101+DB-100 together (Package already assemble GS-101 with DB-100) VESA 75x75 2nd display bracket for G series
B49: 7900GR1040000 | C49: GR-104/Black/GP | D49: 15 | E49: For CD-70, CD-101C bracket for G4 only (VFD position)
B50: 7905000000025 | C50: VESA Bracket Kit/100-75/M4 Screw/Black | E50: Supporting plate to convert VESA 75x75 to 100 x 100, MOQ 20pcs
B51: G4 2D Scanner and Camera when position as Landscape mode
B52: 79050A7199216 | C52: SCN-300/2D(N4680)/A4,A7,G4,G5/1.1/B+G | D52: 115 | E52: 2D Scanner - install at the Top / Right / Left-hand side of Screen. Same as A series
B53: 79050A7199325 | C53: CAMERA-300/8M/AV5180A1D/A4,A7,G4,G5/1.1/B+G/GP | D53: 55 | E53: Camera - install at the Top / Right-hand of Screen
B54: Expansion IO Box for G series
B55: 7900EX100G200 | C55: EX-100-G/Power USBx4+180W Kit/GP Powered USB (install underneath G series Base) | D55: 110 | E55: For G series existing base
B56: 7900EX101G300 | C56: EX-101-G/USB3.0x7+120W Kit/GP USB 3.0 x 7 (install underneath G series Base) | D56: 88 | E56: For G series existing base
B57: Stand | D57: ITP | E57: Remark
B58: 79050A5230000 | C58: T Base Kit/Black/W/O Logo/GP | D58: 30 | E58: T base in industrial packing (6pcs in one carton), MOQ 6pcs
B59: 79050A5230001 | C59: T Base Kit/Black/Partner Logo/GP | D59: 30 | E59: T base in industrial packing (6pcs in one carton), MOQ 6pcs
B60: 79050G4131000 | C60: D Stand Kit/Black/Partner Logo/GP -(1箱可裝5個) | D60: 33 | E60: D base in industrial packing (5pcs in one carton), MOQ 5pcs
B61: 7905xxxxxxxxx | C61: G5+D base - (1箱1個) | D61: 45 | E61: D base in G5 standard packing
B62: 7905xxxxxxxxx | C62: G4+D base - (1箱1個) | D62: 45 | E62: D base in G4 standard packing
B63: Adapter | D63: ITP | E63: Remark
C64: 180W adapter | D64: 44
C65: 120W adapter | D65: =D66+8 -> 32
C66: 90W adapter | D66: =D67+8 -> 24
C67: 65W adapter | D67: 16

Sheet Audrey-2 Peripherals
A1: Date: | B1: New
B2: A5-2 10.1" 2nd Display (A5-2 needs AR-200 separately) | D2: ITP | E2: Remark
B3: 2614151101313 | C3: CD-101C+JST Cable Only/9cm/NO Logo/Black/1.1/G+ | D3: =88.75+5+15 -> 108.75 | E3: *Need to order AR-200
B4: 2614151101314 | C4: CD-101C+JST Cable Only/PCT/9cm/NO Logo/Black/1.1/G+ | D4: =113.75+5+15 -> 133.75
B5: 2614151101317 | C5: CD-101C+JST Cable Only/9cm/Partner Logo/Black/1.1/G+ | D5: 109 | E5: W/Partner logo
B6: 2614151101318 | C6: CD-101C+JST Cable Only/PCT/9cm/Partner Logo/Black/1.1/G+ | D6: =113.75+5+15 -> 133.75 | E6: W/Partner logo
B7: A5-2 Regular Peripherals | D7: ITP | E7: Remark
B8: 79050A5291100 | C8: MSR Module/ID123(Beep)/A5-2-E,T/Black/GP | D8: 30 | E8: *Default beep sound off
B9: 790W50A520001 | C9: VFD Module/WDM-M2027/5V/RS232/A5-2/1.1/Black C/GP | D9: 50
B10: 79050A5291700 | C10: Multi Reader/ID123(Beep)+RFID(RF-551V)/A5-2/Black/GP | D10: 80 | E10: *Default beep sound off *IC Card slot is covered with mylar
B11: 79050A5291800 | C11: Multi Reader/ID123(Beep)+EMV IC Card/A5-2/Black/GP | D11: 80 | E11: *Default beep sound off
B12: 79050A5299300 | C12: Power USB Kit/A5-2/GP | D12: 25 | E12: Power USB 12Vx1, 24Vx1 (*Needs to upgrade adapter to 180W) *Only available on A5-2-T/ A5-2-E/ V5-1-T/ V5-1-E
B13: 7900AR2000001 | C13: AR-200/1.1/Black/GP | D13: 15 | E13: For T & D stand VESA 75x75 2nd display bracket for A5-2 series (Plastic!!!) | F13: =(D13-#REF!)/D13 -> #REF!
B14: 7900AR2000002 | C14: AR-200/AL/Black/GP | D14: 15 | E14: For T & D stand VESA 75x75 2nd display bracket for A5-2 series (Metal!!)
B15: 79050A5199104 | C15: Wifi+BT Kit/6E AX210/Ax-E,AL,T,C10-1E/GP(W/O M.2-PCIE) | D15: 25 | E15: WIFI 6, Alder Lake / Elkhart Lake/ TigerLake/ N97 & N305 only support WIFI 6E (W/O M.2 to PCIe board)
B16: 79050A5291402 | C16: Multi Reader/RFID(RF320HK-PT3)/A5-2/Black/GP | D16: 45 | E16: *Giga RFID (Single Band) *MSR slot is covered by mylar
B17: A5-2 By MOQ Peripherals | D17: MOQ 50pc | E17: Remark
B18: 7900AS2000000 | C18: AS-200/Black/GP | D18: MOQ 1pcs: 45 MOQ 5pcs: 25 MOQ 20pcs: 20 | E18: VESA 75x75 2nd display bracket for A-2 series
B19: 79050A5291400 | C19: RFID Module/RFID(RF-551V)/A5-2/Black/GP | D19: MOQ 1pcs: 125 MOQ 5pcs: 125 MOQ 20pcs: 65
B20: 79050A5291300 | C20: BIO Module/Fingerprint/A5-2/Black/GP | D20: MOQ 1pcs: 135 MOQ 5pcs: 125 MOQ 20pcs: 105 MOQ 50pcs: 90
B21: 79050A5291600 | C21: iButton(Probe) Kit/A5-2/Black/GP | D21: MOQ 1pcs: 90 MOQ 5pcs: 75 MOQ 20pcs: 55 MOQ 50pcs: 45
B22: 79050A5291601 | C22: iButton(Magnetic Probe) Kit/A5-2/Black/GP | D22: MOQ 1pcs: 85 MOQ 5pcs: 75 MOQ 20pcs: 60 MOQ 50pcs: 45
B23: 79050A5292000 | C23: IO Bracket+Cable Kit/COMx3/A5-2/GP | D23: 10
B24: 79050A5292001 | C24: IO Bracket+Cable Kit/COM3+COM4/A5-2,J14-1/GP | D24: 14 | E24: The kit is bought separately for rework.
B25: Bult-in | C25: COM3+COM4/A5-2,J14-1/GP | D25: 7 | E25: If COM3+COM4 are built in in the terminal at PTT, the price will be lower as the IO bracket is included already.
B26: 79050A5292100 | C26: IO Bracket+Cable Kit/USB7+USB8/A5-2/GP | D26: 8 | E26: MOQ: 200pcs
B27: 7905000000021 | C27: Addimat key module Kit on Side/PTE/Black/GP | D27: 5pcs: 26 20pcs: 17.5 100pcs: 15
B28: 79050A5299801 | C28: VP3350 case Kit/A5-2/Black/GP | D28: MOQ 1pcs: $60 MOQ 2pcs: $28 MOQ 10ocs: $20 MOQ 30pcs: $18 MOQ 50pcs: $16 MOQ 100pcs: $15
B29: A5-2 2D Scanner and Camera when position as Landscape mode (must purchase additional Kit + Scanner/Camera)
B30: A5-2 By MOQ Connection Kit | D30: ITP | E30: Remark
B31: 79050A5299400 | C31: Side Conn Kit/2D,Camera,Light/A5-2/Black/GP | D31: 5pcs: 20 30pcs: 12 50pcs" 10 100pcs: 9 500pcs: 8 | E31: Side Kit to install SCN-300 or CAMERA-300 at the Right/Left-hand of Screen (need to purchase SCN-300 or CAMERA-300 separately)
B32: 79050A5299401 | C32: Up Conn Kit/2D,Camera,Light/A5-2/Black/GP | D32: 25 | E32: MOQ 25pcs Side Kit to install SCN-300 or CAMERA-300 at the Top/VFD of Screen (need to purchase SCN-300 or CAMERA-300 separately)
B33: 79050A7199216 | C33: SCN-300/2D(N4680)/A4,A7,G4,G5/1.1/B+G | D33: 115 | E33: 2D Scanner - install with 79050A5299400 or 79050A5299401 additional kit
B34: 79050A7199325 | C34: CAMERA-300/8M/AV5180A1D/A4,A7,G4,G5/1.1/B+G/GP | D34: 55 | E34: Camera - install with 79050A5299400 or 79050A5299401 additional kit
B35: 79050A5299802 | C35: Payment VESA Bracket/A5-2 on PS103/Black/G | D35: 1pcs: 28 5pcs: 18 10pcs: 16 20pcs: 15
B36: Stand | D36: ITP | E36: Remark
B37: 79050A5230000 | C37: T Base Kit/Black/W/O Logo/GP | D37: 30 | E37: T base in industrial packing (6pcs in one carton), MOQ 6pcs
B38: 79050A5230001 | C38: T Base Kit/Black/Partner Logo/GP | D38: 30 | E38: T base in industrial packing (6pcs in one carton), MOQ 6pcs
B39: 79050A5103005 | C39: A Base Kit/New Hinge Cover/B+G/Partner Logo/GP | D39: 40 | E39: A base in industrial packing (4pcs in one carton), MOQ 4pcs *Cannot be applied on A7!!! *New stand is easier for service (do not need to take out stand to be able to change the RAM/SSD)
B40: RAID (Only for A5-2-M/A4-2-M/A7-2-M/V5-2-M | D40: ITP | E40: Remark
B41: TBD | C41: RAID bracket | D41: 5
B42: Adapter | D42: ITP | E42: Remark
C43: 180W adapter | D43: 44
C44: 120W adapter | D44: =D45+8 -> 32
C45: 90W adapter | D45: =D46+8 -> 24
C46: 65W adapter | D46: 16

Sheet J14 Peripherals
A1: Date: | B1: New
B2: J14 10.1" 2nd Display (A5-2 needs AR-200 separately) | D2: ITP | E2: Remark
B3: 2614151101313 | C3: CD-101C+JST Cable Only/9cm/NO Logo/Black/1.1/G+ | D3: =88.75+5+15 -> 108.75 | E3: *Need to order AR-200
B4: 2614151101314 | C4: CD-101C+JST Cable Only/PCT/9cm/NO Logo/Black/1.1/G+ | D4: =113.75+5+15 -> 133.75
B5: 2614151101317 | C5: CD-101C+JST Cable Only/9cm/Partner Logo/Black/1.1/G+ | D5: 109 | E5: W/Partner logo
B6: 2614151101318 | C6: CD-101C+JST Cable Only/PCT/9cm/Partner Logo/Black/1.1/G+ | D6: =113.75+5+15 -> 133.75 | E6: W/Partner logo
B7: J14 Regular Peripherals (Share the same peripherals with A5-2) | D7: ITP | E7: Remark
B8: 79050A5291100 | C8: MSR Module/ID123(Beep)/A5-2-E,T/Black/GP | D8: 30 | E8: *Default beep sound off
B9: 790W50A520001 | C9: VFD Module/WDM-M2027/5V/RS232/A5-2/1.1/Black C/GP | D9: 50
B10: 79050A5291700 | C10: Multi Reader/ID123(Beep)+RFID(RF-551V)/A5-2/Black/GP | D10: 80 | E10: *Default beep sound off *IC Card slot is covered with mylar
B11: 79050A5291800 | C11: Multi Reader/ID123(Beep)+EMV IC Card/A5-2/Black/GP | D11: 80 | E11: *Default beep sound off
B12: 79050A5299300 | C12: Power USB Kit/A5-2/GP | D12: 25 | E12: Power USB 12Vx1, 24Vx1 (*Needs to upgrade adapter to 180W)
B13: 7900AR2000001 | C13: AR-200/1.1/Black/GP | D13: 15 | E13: VESA 75x75 2nd display bracket for A5-2 series (Plastic!!!) | F13: =(D13-#REF!)/D13 -> #REF!
B14: 7900AR2000002 | C14: AR-200/AL/Black/GP | D14: 15 | E14: VESA 75x75 2nd display bracket for A5-2 series (Metal!!)
B15: 79050A5199104 | C15: Wifi+BT Kit/6E AX210/Ax-E,AL,T,C10-1E/GP(W/O M.2-PCIE) | D15: 25 | E15: WIFI 6, Alder Lake / Elkhart Lake/ TigerLake/ N97 & N305 only support WIFI 6E (W/O M.2 to PCIe board)
B16: 79050A5291402 | C16: Multi Reader/RFID(RF320HK-PT3)/A5-2/Black/GP | D16: 45 | E16: *Giga RFID (Single Band) *MSR slot is covered by mylar
B17: J14 By MOQ Peripherals (Share the same peripherals with A5-2) | D17: MOQ 50pc | E17: Remark
B18: 79050A5291400 | C18: RFID Module/RFID(RF-551V)/A5-2/Black/GP | D18: MOQ 1pcs: 125 MOQ 5pcs: 125 MOQ 20pcs: 65
B19: 79050A5291300 | C19: BIO Module/Fingerprint/A5-2/Black/GP | D19: MOQ 1pcs: 135 MOQ 5pcs: 125 MOQ 20pcs: 105 MOQ 50pcs: 90
B20: 79050A5291600 | C20: iButton(Probe) Kit/A5-2/Black/GP | D20: MOQ 1pcs: 90 MOQ 5pcs: 75 MOQ 20pcs: 55 MOQ 50pcs: 45
B21: 79050A5291601 | C21: iButton(Magnetic Probe) Kit/A5-2/Black/GP | D21: MOQ 1pcs: 85 MOQ 5pcs: 75 MOQ 20pcs: 60 MOQ 50pcs: 45
B22: 79050A5292000 | C22: IO Bracket+Cable Kit/COMx3/A5-2/GP | D22: 10
B23: 79050A5292001 | C23: IO Bracket+Cable Kit/COM3+COM4/A5-2,J14-1/GP | D23: 14 | E23: The kit is bought separately for rework.
B24: Bult-in | C24: COM3+COM4/A5-2,J14-1/GP | D24: 7 | E24: If COM3+COM4 are built in in the terminal at PTT, the price will be lower as the IO bracket is included already.
B25: 79050A5292100 | C25: IO Bracket+Cable Kit/USB7+USB8/A5-2/GP | D25: 8 | E25: MOQ: 200pcs
B26: 7905000000021 | C26: Addimat key module Kit on Side/PTE/Black/GP | D26: 5pcs: 26 20pcs: 17.5 100pcs: 15
B27: 79050A5299801 | C27: VP3350 case Kit/A5-2/Black/GP | D27: MOQ 2pcs: 28
B28: A5-2 2D Scanner and Camera when position as Landscape mode (must purchase additional Kit + Scanner/Camera)
B29: A5-2 By MOQ Connection Kit | D29: ITP | E29: Remark
B30: 79050A5299400 | C30: Side Conn Kit/2D,Camera,Light/A5-2/Black/GP | D30: 5pcs: 20 30pcs: 12 50pcs" 10 100pcs: 9 500pcs: 8 | E30: Side Kit to install SCN-300 or CAMERA-300 at the Right/Left-hand of Screen (need to purchase SCN-300 or CAMERA-300 separately)
B31: 79050A5299401 | C31: Up Conn Kit/2D,Camera,Light/A5-2/Black/GP | D31: 25 | E31: MOQ 25pcs Side Kit to install SCN-300 or CAMERA-300 at the Top/VFD of Screen (need to purchase SCN-300 or CAMERA-300 separately)
B32: 79050A7199216 | C32: SCN-300/2D(N4680)/A4,A7,G4,G5/1.1/B+G | D32: 115 | E32: 2D Scanner - install with 79050A5299400 or 79050A5299401 additional kit
B33: 79050A7199325 | C33: CAMERA-300/8M/AV5180A1D/A4,A7,G4,G5/1.1/B+G/GP | D33: 55 | E33: Camera - install with 79050A5299400 or 79050A5299401 additional kit
B34: 79050A5299802 | C34: Payment VESA Bracket/A5-2 on PS103/Black/G | D34: 1pcs: 28 5pcs: 18 10pcs: 16 20pcs: 15
B35: Stand | D35: ITP | E35: Remark
B36: 79050A5230000 | C36: T Base Kit/Black/W/O Logo/GP | D36: 30 | E36: T base in industrial packing (6pcs in one carton), MOQ 6pcs
B37: 79050A5230001 | C37: T Base Kit/Black/Partner Logo/GP | D37: 30 | E37: T base in industrial packing (6pcs in one carton), MOQ 6pcs
B38: 79050A5103005 | C38: A Base Kit/New Hinge Cover/B+G/Partner Logo/GP | D38: 40 | E38: A base in industrial packing (4pcs in one carton), MOQ 4pcs *Cannot be applied on A7!!! *New stand is easier for service (do not need to take out stand to be able to change the RAM/SSD)
B39: Adapter | D39: ITP | E39: Remark
C40: 180W adapter | D40: 44
C41: 120W adapter | D41: =D42+8 -> 32
C42: 90W adapter | D42: =D43+8 -> 24
C43: 65W adapter | D43: 16
B44: IO Cover | D44: ITP | E44: Remark
B45: 2500350J41100 | C45: I/O Cover/J14-1/Black/G+ | D45: 2.5

Sheet C Series Peripherals
A1: Date: | B1: New
B2: C series Peripherals | D2: ITP | E2: Remark
B3: 79090C1191100 | C3: MSR Module/ID123/C10-1/Black/GP | D3: 30 | E3: MSR only
B4: 79090C1194200 | C4: Fingerprint Module/C10-1/White/GP | D4: 80 | E4: Fingerprint only
B5: 7909070193400 | C5: IC Card(ID) Module/PAT-120/White/GP | D5: 48 | E5: IC Card only
B6: 79090C1195100 | C6: NFC(RF-551V) Module/C10-1/White/GP | D6: 50 | E6: RFID/NFC Only
B7: 7909070195200 | C7: NFC(MP30H-PT) Module/PAT-120/White/GP | D7: 50 | E7: *For PTE Dangot only
B8: 79090C1196200 | C8: 2nd Display/10.1"/CD-101CG/C10-1/White/GP | D8: =113+16+2 -> 131 | E8: 2nd Display Hinge/ARM only + CD-101C white/silver w/o touch | F8: =#REF!/0.8 -> #REF!
B9: 79090C1196250 | C9: 2nd Display/10.1"/CD-101/PCT/C10-1/White/GP | D9: =138+16+2 -> 156 | E9: 2nd Display Hinge/ARM only + CD-101C white/silver with touch
B10: 79090C1199200 | C10: 2nd Hinge For CD101/C10-1/White/GP | D10: 25 --> 16 | E10: 2nd Display Hinge/ARM only
B11: 79050A5199104 | C11: Wifi+BT Kit/6E AX210/GP(E5/Ax/Gx-K/A/B/E/T/AL,BW-xxx-W,C1x-E) | D11: 25 | E11: WIFI 6, Alder Lake / Elkhart Lake/ TigerLake/ N97 & N305 only support WIFI 6
B12: 79090C1196100 | C12: VFD Module/CD7220/BOE/12V/White/C10,C14/W/O Logo/GP | D12: 50 | E12: MOQ: 300pcs
B13: 79090C1199201 | C13: CD7220 Connection Kit/C10,C14/White/GP | D13: MOQ 2pcs: $30 MOQ 30pcs: $16 MOQ 300pcs: $10
B14: 2D Scanner and Camera
B15: 2100490C11400 | C15: Cable Cover/SCN300 for C10/White | D15: 5 | E15: White cable cover bracket for SCN-300 & CAMERA-300
B16: 79090C1198101 | C16: SCN-300/2D(N4680)/C10,C14/1.1/B+G/GP | D16: 118 | E16: *2D Scanner - install at the Top / Right / Left-hand side of Screen. *w/ white cable cover bracket
B17: 79050A7199216 | C17: SCN-300/2D(N4680)/A4,A7,G4,G5/1.1/B+G | D17: 115 | E17: *2D Scanner - install at the Top / Right / Left-hand side of Screen. *w/o white cable cover bracket, need to order cable cover bracket
B18: 79090C1198100 | C18: SCN-300/2D(N4680)/C10,C14/1.1/White/GP | D18: 120 | E18: *2D Scanner - install at the Top / Right / Left-hand side of Screen *w/ white cable cover bracket
B19: 79050A7199220 | C19: SCN-300/2D(N4680)/A4,A7,G4,G5/1.1/White/GP | D19: 117 | E19: *2D Scanner - install at the Top / Right / Left-hand side of Screen *w/o white cable cover bracket, need to order cable cover bracket
B20: 79050A7199325 | C20: CAMERA-300/8M/AV5180A1D/A4,A7,G4,G5/1.1/B+G/GP | D20: 55 | E20: *Camera - install at the Top / Right / Left-hand side of Screen. *w/o white cable cover bracket, need to order cable cover bracket
B21: New P/N | C21: CAMERA-300/8M/AV5050A22/C10,C14/1.1/B+G/GP | D21: 58 | E21: *Camera - install at the Top / Right / Left-hand side of Screen. *w/ white cable cover bracket, need to order cable cover bracket
B22: New P/N | C22: CAMERA-300/8M/AV5050A22/A4,A7,G4,G5/1.1/White | D22: 57 | E22: *Camera - install at the Top / Right / Left-hand side of Screen. *MOQ 300pcs *w/o white cable cover bracket, need to order cable cover bracket
B23: 79090C119C106 | C23: CAMERA-300/8M/AV5180A1D/C10,C14/1.1/White/GP | D23: =D22+3 -> 60 | E23: *Camera - install at the Top / Right / Left-hand side of Screen. *MOQ 300pcs *w/ white cable cover bracket, need to order cable cover bracket
B24: 79090C119P000 | C24: Payment Bracket Kit/N6/C10-1/Black/GP | D24: 1~4pcs: $58 5~9pcs: $34 10~19pcs: $27 >=20pcs: $25 | E24: Payment Bracket for PTU only

Sheet BOX PC Alfa Peripherals
A1: Date | B1: NEW
A4: Alfa By MOQ Peripherals | C4: ITP | D4: Remark
A5: 79050AB109100 | B5: Wall Mount Bracekt | C5: MOQ 5pcs: 18
C6: MOQ 10pcs: 16
C7: MOQ 50pcs: 13
C8: MOQ 100pcs: 12
A10: RAID | B10: ITP UP
A11: Upgrade to RAID (BRACKET ONLY) | B11: 1pcs 7 50pcs 5 100pcs 5 200pcs 5
A12: Additional 128G SSD | B12: TBD
A13: Additional 256G SSD | B13: TBD
A14: Additional 512G SSD | B14: TBD
A15: Additional 1TB SSD | B15: TBD

Sheet License
A1: Confidential Information for Partner Tech Internal Use Only!
A4: OS | B4: Description | C4: Corresponding P/N | E4: Remark
D5: ITP
A6: OS | B6: 2021 H2 WIN 10 please refer to below table for Corresponding CPUs list
A7: OS | B7: Win10 IoT Ent 2021 LTSC MultiLang ESD OEI "Entry" EPKEA Entry for Selected ATOM, Selected Celeron (J6412, J1900, J3455, N2807, G3900, G3900TE, 3955U, 3865U) version | C7: 2619510600017 | D7: 33.5
A8: OS | B8: Win10 IoT Ent 2021 LTSC MultiLang ESD OEI "Value" EPKEA Value for Selected Atom, Selected Celeron, Pentium, Core i3, Core i5 version | C8: 2619510600018 | D8: 67
A9: OS | B9: Win10 IoT Ent 2021 LTSC MultiLang ESD OEI "High End" EPKEA High for Core i7 | C9: 2619510600019 | D9: 130
A10: OS | B10: Windows® 11
A11: OS | B11: Win11 IoT Ent MultiLang ESD OEI Entry EPKEA Entry for Selected ATOM, Selected Celeron J6412 | C11: 2619510700000 | D11: 33.5
A12: OS | B12: Win11 IoT Ent MultiLang ESD OEI Value EPKEA Value for Selected Atom, Selected Celeron, Pentium, Core i3, Core i5 version | C12: 2619510700001 | D12: 67
A13: OS | B13: Win11 IoT Ent MultiLang ESD OEI High End EPKEA High for Core i7 | C13: 2619510700002 | D13: 130
A14: OS | B14: Win Pro 11 64-bit, 英文隨機版(DVD), 英式鍵盤, FQC-10528 | C14: FQC-10528 | D14: 165
A15: OS | B15: Win Pro 11 64-bit, 英文隨機版(DVD), 美式鍵盤, FQC-10529 | C15: FQC-10529 | D15: 165
A16: OS | B16: Win11 IoT Ent 2024 LTSC MultiLang ESD OEI Entry EPKEA | C16: 2619510701000 | D16: 33.5
A17: OS | B17: Win11 IoT Ent 2024 LTSC MultiLang ESD OEI Value EPKEA | C17: 2619510701001 | D17: 67
A18: OS | B18: Win11 IoT Ent 2024 LTSC MultiLang ESD OEI High End EPKE | C18: 2619510701002 | D18: 130
A19: OS | B19: Win11 IoT Ent 2024 LTSC MultiLang ESD OEI Entry Upgrade EPKEA | C19: 2619510701100 | D19: 33.5
A20: OS | B20: Win11 IoT Ent 2024 LTSC MultiLang ESD OEI Value Upgrade EPKEA | C20: 2619510701101 | D20: 67
A21: OS | B21: Win11 IoT Ent 2024 LTSC MultiLang ESD OEI High End Upgrade EPKEA | C21: 2619510701102 | D21: 130
A22: OS | B22: Win 11 Pro GAC - Microsoft Windows 11 Pro 64 Bit English OEM DVD 1-Pack(FQC-10529) | C22: 2619500700000 | D22: 185
... A25: OS | B25: Windows Server® IoT 2022 Remote Desktop Services Client Access License (1 User) (ESD) | C25: 6VC-04363 | D25: 98

Sheet M10
A1: Date: | B1: New
A3: Product | B3: Product/Description | C3: 參考資料
A4: Model | B4: Description | C4: Corresponding P/N | E4: Remark
D5: ITP
A6: M10 | B6: M10 Standard Terminal
A7: M10 | B7: M10-3N/N200/8G/128G/XYC/350nits/ADV/W-I6/Battery/US/Partner Logo | C7: TBD | D7: TBD
A8: M10 | B8: M10-3N/N200/8G/128G/XYC/350nits/ADV/W-I6/Battery/US/Win11/Partner Logo | C8: TBD | D8: TBD
A9: M10 | B9: M10-3N/N200/8G/128G/XYC/800nits/ADV/W-I6/Battery/US/Partner Logo | C9: TBD | D9: TBD | E9: 800nits MOQ 500pcs
A10: M10 | B10: M10-3N/N200/8G/128G/XYC/800nits/ADV/W-I6/Battery/US/Win11/Partner Logo | C10: TBD | D10: TBD | E10: 800nits MOQ 500pcs
A11: M10 | B11: M10-3N/N300/16G/512G/XYC/350nits/ADV/W-I6/Battery/US/Partner Logo | C11: TBD | D11: TBD | E11: MOQ 300pcs Market Price Need to requote when there is a project.
A12: M10 | B12: 128G to 256G | C12: TBD | D12: TBD | E12: MOQ 500pcs Market Price Need to requote when there is a project.
A13: M3w-2 & M10 | B13: M3w-2 & M10 Optional Peripherals
A14: M3w-2 & M10 | B14: Main Battery (Li Battery Pack/7.4v/4600mA/BP18-002240/M3/GP) | C14: 1380210740000 | D14: 55
A15: M10 | B15: MSR Module/ID123/M10-3N/Black/Partner Logo/GP | C15: 79090M1039210 | D15: 30
A16: M10 | B16: EMV IC Card/MINI2-50-P1/M10-3N/GP | C16: 79090M1039310 | D16: 40
A17: M10 | B17: (Rear Cover+Fingerprint Kit/ w/o battery cover/M10/Black/G | C17: TBD | D17: 85 | E17: *No tooling yet *Rear cover MOQ: 300pcs *Fingerprint module MOQ: 180pcs *Need to change rear cover when add fingerprint
A18: M10 | B18: NFC Module/RF-551V/M10/GP | C18: 79090M1039610 | D18: 35
A19: M10 | B19: Scanner/2D/SE2707/M10-3N/Black/GP | C19: 79090M1039420 | D19: 80
A20: M10 | B20: Front Camera/5M/M10-3N/GP | C20: 79090M1039110 | D20: 100pcs: 35 500pcs: 32 | E20: MOQ: 100pcs / 500pcs
A21: M10 | B21: Rear Camera/8M/M10-3N/GP | C21: 79090M1039120 | D21: 100pcs: 42 500pcs: 35 | E21: MOQ: 100pcs / 500pcs
A22: M10 | B22: 4G LTE-A Cat6 Module Kit/EM060K-NA/North America/M10-3N/GP | C22: 79090M1039810 | D22: 65 | E22: Antenna MOQ: 500pcs
A23: M10 | B23: 5G Sub-6 Module/RM520N-GL/M10-3N/GP | C23: 79090M1039820 | D23: 190 | E23: Antenna MOQ: 500pcs
A24: M3w-2 & M10 | B24: Handstrap (same as EM-100/300) - New Hand Strap/Elastic/EM-100,300/GP | C24: 7909036619000 | D24: 8
A25: M3w-2 & M10 | B25: Shoulder Strap/EM-100/1.2/GP | C25: 25090A1903663 | D25: 4.5
A26: M3w-2 & M10 | B26: Sunblock Cover/M3/Black/G+ | C26: 25090A190M301 | D26: 19
A27: M3w-2 & M10 | B27: Wall Mount Kit/M3W,M3A/Black/GP | C27: 79090M3099200 | D27: 22 | E27: MOQ 20pcs
A28: M10 | B28: Payment Bracket Kit/MOBY550/M10-3N/Black/GP | C28: 79090M1039726 | D28: 1pcs: $40 5pcs: $25 30pcs: $20 50pcs: $18 | E28: *EXW TW
A29: M10 | B29: Payment Bracket Kit/Link2500/M10-3N/Black/GP | C29: 79090M1039725 | D29: 1pcs: $50 5pcs: $35 30pcs: $25 50pcs: $22 | E29: *EXW TW
A30: M10 | B30: Payment Bracket Kit/VP3300/M10-3N/Black/GP | C30: 79090M1039727 | D30: 1pcs: $52 5pcs: $38 30pcs: $28 50pcs: $25 | E30: *EXW TW
A31: M10 | B31: Payment Bracket Kit/E285/M10-3N/Black/GP | C31: 79090M1039723 | D31: 1pcs: $65 5pcs: $48 30pcs: $32 50pcs: $20 | E31: *EXW TW
A32: M10 | B32: Payment Bracket Kit/VP3350/M10-3N/1.1/Black/GP | C32: 79090M1039728 | E32: *EXW TW
A33: M3w-2 & M10 | B33: Battery Charging Cradle - Charging Cradle/CBE-1/US/Black/GP (up to 5 Batteries) | C33: 79090CBE11000 | D33: N/A | E33: EOL
A34: M3w-2 & M10 | B34: New charging cradle - Charging cradle/M10-3N/US/Black/GP | C34: 79090M1039C00 | D34: 18
A35: M3w-2 & M10 | B35: X3-10 POS Base X3-10/US/Partner Logo/1.1/GP (NEW) Must purchase with Hand Strap 7909036619000 for locking purpose | C35: 7909070400300 | D35: 165 | E35: MOQ: 300pcs | G35: =#REF!/0.85 -> #REF!
A36: M3w-2 & M10 | B36: X3-30 POS Base X3-20/US/Partner Logo/1.1/GP (NEW) Must purchase with Hand Strap 7909036619000 for locking purpose | C36: 7909070401300 | D36: 195 | E36: MOQ: 300pcs PO MOQ: 20pcs

Sheet KDS A5 & A7 Steam Proof
A1: Date | B1: 45736
B3: ITP | C3: ITP | D3: ITP | E3: ITP
A4: Item | B4: MOQ 1 pcs | C4: MOQ 5 pcs | D4: MOQ 10 pcs | E4: MOQ 25 pcs
A5: A5 KDS kit (POS not included) | B5: 270 | C5: 135 | D5: 130 | E5: 125
A6: A7 KDS kit (POS not included) | B6: 290 | C6: 145 | D6: 140 | E6: 135
A9: Model | B9: 料號 | C9: 項目 | D9: ITP (USD)
A10: A5 Sealing kit only | B10: 25080550A5001 | C10: CR+Adhesive(G4000)/Rear Cover/362x2.8x1mm/A5-1/GP | D10: 5
C11: 防水膠
A12: Total
A15: Model | B15: 料號 | C15: 項目 | D15: ITP (USD)
A16: A7 Sealing kit only | B16: 25080550A5001 | C16: CR+Adhesive(G4000)/Rear Cover/362x2.8x1mm/A5-1/GP | D16: 8
C17: 防水膠
A18: Total

Sheet PS-103.107 Stand
A1: Date | B1: New
B3: For any models other than SP-600 series and A7
D5: ITP | E5: ITP | F5: ITP | G5: ITP | H5: ITP
D6: MOQ 1pcs | E6: MOQ 5pcs | F6: MOQ 10pcs | G6: MOQ 30pcs | H6: MOQ 50pcs
B7: Printer Stand PS-103 | C7: (A+B) PS-103/Power USBx4/180W/1.1/Black+Silver/W/O Logo/GP Set) 790PS10311000 PS-103/Power USBx4/180W/Black/W/O Logo/G | D7: =D8+D9 -> 207 | E7: =E8+E9 -> 164 | F7: =F8+F9 -> 162 | G7: =G8+G9 -> 159 | H7: =H8+H9 -> 159
C8: A. PS-103 Stand (with bracket support RP-700/ RP-710/ TM-M30) 790PS10310000 PS-103/1.1/Black+Silver/W/O Logo/GP | D8: =D10+45 -> 115 | E8: =E10+45 -> 72 | F8: =F10+45 -> 70 | G8: =G10+45 -> 67 | H8: =H10+45 -> 67
C9: B. Powered USB Kit + 24V Powered USB Y-Cable + 180W adaptor 7905000091002 Power USBx4+180W Kit For Stand/120cm/GP(PS1xx/E5/SP1060/SP1030) | D9: =SUM(D11:D13) -> 92 | E9: =SUM(E11:E13) -> 92 | F9: =SUM(F11:F13) -> 92 | G9: =SUM(G11:G13) -> 92 | H9: =SUM(H11:H13) -> 92
B10: Printer Bracket for RP-710 & TM-M30 | C10: C. Printer bracket for RP-710 & TM-M30 (RP-700 do not need to purchase this bracket) 790PS10309600 Printer Bracket Kit/RP700+RP710+TM-M30 III/PS-103/Black/GP | D10: 70 | E10: 27 | F10: 25 | G10: 22 | H10: 22
B11: Part B Key Components Breakdwon | C11: 12Vx3 24Vx1 Powered USB Kit | D11: =35 -> 35 | E11: =35 -> 35 | F11: =35 -> 35 | G11: =35 -> 35 | H11: =35 -> 35
C12: Powered USB Y-Cable | D12: 13 | E12: 13 | F12: 13 | G12: 13 | H12: 13
C13: 180W Adaptor | D13: 44 | E13: 44 | F13: 44 | G13: 44 | H13: 44
C14: Remark: The thermal printers should be purchased separately.
E15: =D9-D12-D13 -> 35
B16: For A7
D17: MOQ 1pcs | E17: MOQ 20pcs | F17: MOQ 50pcs
D18: ITP | E18: ITP | F18: ITP
B19: Printer Stand PS-107 | C19: (A+B) PS-107 Whole Set (Including Power USB Set) 790PS10701000 PS-107/Power USBx4/180W/Black/W/O Logo/GP | D19: =SUM(D20:D21) -> 367 | E19: =SUM(E20:E21) -> 222 | F19: =SUM(F20:F21) -> 212
C20: A. PS-107 Stand Only 790PS10700000 PS-107/Black/W/O Logo/GP | D20: 275 | E20: 130 | F20: 120
C21: B. Powered USB Kit + 24V Powered USB Y-Cable + 180W adaptor 7905000091002 Power USBx4+180W Kit For Stand/120cm/GP(PS1xx/E5/SP1060/SP1030) | D21: =SUM(D22:D24) -> 92 | E21: =SUM(E22:E24) -> 92 | F21: =SUM(F22:F24) -> 92
B22: Part B Key Components Breakdwon | C22: 12Vx3 24Vx1 Powered USB Kit | D22: 35 | E22: 35 | F22: 35
C23: Powered USB Y-Cable | D23: 13 | E23: 13 | F23: 13
C24: 180W Adaptor | D24: 44 | E24: 44 | F24: 44
C25: Remark: The thermal printers should be purchased separately.

Sheet External IO BOX
B3: For all Partner Tech model
D4: P/N | E4: Standard ITP | F4: Remark
B5: Reguar Spec. | C5: EX-300/Power USB+DC 12V out Option 1 - Detail IO please refer to below photo | D5: 7900EX3000100 | E5: 170 | F5: MOQ 10pcs
C6: EX-300/USB3.0 Option 2 - Detail IO please refer to below photo | D6: 7900EX3000200 | E6: 150
B7: Special Spec. | C7: EX-300/Power USB+DC 12V out/3 in 1 Cable 3M | D7: 7900EX3000105 | E7: 186.4
C8: EX-300/Power USB+DC 12V out/3 in 1 Cable 3M/W/O Adaptor | D8: 7900EX3000103 | E8: 153.14 | H8: =E6+(E7-E5) -> 166.4
C9: EX-300/Power USB+DC 12V out/RS232 DC 12V(Fix COM)/3 in 1 Cable 3M/PTE/Metro II | D9: 7900EX3000110 | E9: 186.4

Sheet Payment Brackets (PTU)
B1: Date | C1: 45558
A3: P/N | B3: Product | C3: 1pcs | D3: 10pcs | E3: 30pcs | F3: 50pcs | G3: 100pcs
C4: ITP | D4: ITP | E4: ITP | F4: ITP | G4: ITP
A5: 7900CD1010001 | B5: VP3300 Holder Kit/CD-101C/Black/GP(A5-1/A4/A7/A5-2/G4/G5/J14/C10/C14) | C5: 15 | D5: 8 | E5: 7 | F5: 6 | G5: 6
A15: P/N | B15: Product | C15: 1pcs | D15: 10pcs | E15: 30pcs | F15: 50pcs | G15: 100pcs
C16: ITP | D16: ITP | E16: ITP | F16: ITP | G16: ITP
A17: 7900CD1010000 | B17: VP3350 Holder Kit/CD-101C/Black/GP | C17: 38 | D17: 20 | E17: 18 | F17: 16 | G17: 12
A30: P/N | B30: Product | C30: 1pcs | D30: 10pcs | E30: 30pcs | F30: 50pcs | G30: 100pcs
C31: ITP | D31: ITP | E31: ITP | F31: ITP | G31: ITP
A32: 79050A5199301 | B32: Payment Bracket Kit/VP-3300 on POS/Black/G+(A5-1/A4/A7/A5-2/G4/G5/J14) | C32: 62 | D32: 30 | E32: 26 | F32: 24 | G32: 19
A47: P/N | B47: Product | C47: 1pcs | D47: 10pcs | E47: 30pcs | F47: 50pcs | G47: 100pcs
C48: ITP | D48: ITP | E48: ITP | F48: ITP | G48: ITP
A49: 79050A5199300 | B49: Payment Bracket Kit/VP-3350 on POS/Black/G+(A5-1/A4/A7/A5-2/G4/G5/J14) | C49: 48 | D49: 23 | E49: 20 | F49: 18 | G49: 15

Sheet IoT (Partner brand)
A1: Cost / ITP 報價參考 -- POS
A2: Confidential Information for Partner Tech Internal Use Only!
A4: 1. 此份報價屬 "極機密性", 勿影印拷貝或供他人參考. | E4: Date: | F4: 45908
A5: 2. 若報價超過此份價格權限請與主管討論.
A6: 3. Warranty: 24months from invoice date.
B8: Product | C8: Product/Description | D8: 參考資料
A9: Category | B9: Model | C9: Description | D9: Corresponding P/N | F9: Remark
E10: ITP
A11: Printer | B11: RP-630 | C11: Triple Interface: USB+COM+Ethernet Black | D11: 930001L14C000 RP-630/B/Eng/S+U+E/Roll/US/Partner Logo/GP | E11: =74+8 -> 82 | F11: If require to ship back to Taiwan, addition $10/pc is required for additional Taiwan BSMI Power Cord and extra freight charges.
B12: RP-630 | C12: USB+COM Only Black | D12: 930001L14C011 RP-630/B/Eng/S(9Pin)+U/Roll/US/Partner Logo/G+ | E12: =74-2 -> 72
B13: RP-630 | C13: Power Adaptor Cover (MOQ 50pcs) | D13: 280RP63000002 Power Adaptor Cover/RP-630/GP | E13: 10
B14: RP-630 | C14: Water-Spill Proof Cover (MOQ 50pcs) | D14: 280RP63000001 Water Spill-Proof Cover/RP-630/GP | E14: 5
B15: RP-700 | C15: Triple Interface: USB+COM+Ethernet Black | E15: =95+8 -> 103
B16: RP-700 | C16: USB+COM only Black | E16: =95-4 -> 91
B17: RP-700 | C17: USB+ BT (Mfi certified) Black or White | E17: 110
B18: RP-700 Optional | C18: Wifi interface card | E18: 52 | F18: Ex-work Term
B19: RP-700 | C19: JK-B02 BlueTooth module（MFI） | D19: 280RP700G0033 Interface card/MFi/RP-700/G+ | E19: 30 | F19: *MOQ 6pcs or multible by 6pcs *This is ITP adder to RP-700
B20: RP-700 | C20: JK-B02 BlueTooth module | D20: 280RP700G0034 Interface card/Bluetooth/RP-700/G+ | E20: 25 | F20: *MOQ 6pcs or multible by 6pcs *This is ITP adder to RP-700
B21: RP-600 | C21: RP-600 | D21: 930001L100100 RP-600/B/Big5/S/US/GP | E21: 95
B22: RP-600 | C22: RP-600 (Ethernet) | D22: 930001L102004 RP-600/B/Eng/Ethernet/EU/GP | E22: =115+8 -> 123
A24: Scanner | B24: WS-100 | C24: Handheld 2D Barcode Scanner with Stand. CMOS sensor | D24: 9601202000002 2D Scanner/WS-100/USB/Stand/Black/Partner Logo | E24: 75 | F24: EOL
B25: WS-200 | C25: 2D Scanner/WS-200/USB/Black/Partner Logo | D25: 92000020WS200 | E25: 34 | F25: *MOQ 200pcs
B26: WS-200 | C26: WS-200 Scanner Stand,Black | D26: 8009200000000 (Temp) | E26: 5 | F26: *No MOQ required
A28: Cash Drawer | B28: FT-465 | C28: FT-465 Cash Drawer | D28: 93030FT465000 Cash Drawer/FT-465/5B8C/Black/GP | E28: 36
C29: FT-465 Lockable Lid | D29: 93032FT465100 Cash Drawer Lockable Lid/FT-465/Black/G+ | E29: 8
B30: 9E-410 | C30: 9E-410 | E30: 33
B31: 5E-415 | C31: 5E-415 | E31: 42 | F31: If RO ship directly, can deduct $2/pc
C32: 5E-415 Lockable Lid | D32: 280CASH000035 Lockable lid key/5E-415,FT-460/GP 280CASH000036 Lockable lid lock/5E-415,FT-460/GP | E32: 12
C33: 5E-415 Inner Tray | D33: 2108520600003 CashDrawer Inner Tray/5B8C/5E415,5E465 | E33: 12
B34: FT-460 | C34: FT-460 | E34: 46 | F34: If RO ship directly, can deduct $2/pc
C35: FT-460 Lockable Lid | D35: 280CASH000035 Lockable lid key/5E-415,FT-460/GP 280CASH000036 Lockable lid lock/5E-415,FT-460/GP | E35: 12
C36: FT-460 Inner Tray | D36: 9303103000010 Cash Drawer Inner Tray/FT-460/5B8C/Black/GP | E36: 12
A38: Customer Display/ Monitor | B38: PMC-1500 Display only | C38: PMC-1500 without Base - Bezel-Free - Support both VGA/HDMI Packing includes VGA/ HDMI/ DC 12V | E38: 136
B39: PMC-1500 with PCT Touch | C39: PMC-1500 without Base - Bezel-Free - Support both VGA/HDMI Packing includes VGA/ HDMI/ DC 12V | E39: 170
B40: PMC-1500 Display only with Power Adaptor | C40: PMC-1500 without Base - Bezel-Free - Support both VGA/HDMI Packing includes VGA/ HDMI/ DC 12V, Power Adaptor | E40: 150
B41: PMC-1500 with PCT Touch with Power Adaptor | C41: PMC-1500 without Base - Bezel-Free - Support both VGA/HDMI Packing includes VGA/ HDMI/ DC 12V, Power Adaptor | E41: 181
B42: PMC-1500 Display only with Power Adaptor | C42: PMC-1500 without Base - Bezel-Free - Support both VGA/HDMI Packing includes VGA/ HDMI/ DC 12V, Power Adaptor | D42: 2614150015310 | E42: 145 | F42: PTAP only, including: 1. VGA cable: 70cm + 180cm 2. HDMI cable: 70cm + 180cm 3. DC to DC cable: 70cm + 180cm 4. Power adapter 5. AC power cord
B43: PMC-1500 with PCT Touch with Power Adaptor | C43: PMC-1500 without Base - Bezel-Free - Support both VGA/HDMI Packing includes VGA/ HDMI/ DC 12V, Power Adaptor | D43: 2614150015311 | E43: 165 | F43: PTAP only, including: 1. VGA cable: 70cm + 180cm 2. HDMI cable: 70cm + 180cm 3. DC to DC cable: 70cm + 180cm 4. Power adapter 5. AC power cord 6. USB cable (touch): 70cm + 180cm
B44: PMC-1500 with PCT Touch with Power Adaptor | C44: PMC-1500/15"/PCT/HDMI 3M,USB 3M/US/1.1/Black/No Logo,VGA,DC/G+ | D44: 2614150015313 | E44: 170 | F44: PTAP only, including: 1. VGA cable: not included 2. HDMI cable: 300cm 3. DC to DC cable: not included 4. Power adapter 5. AC power cord 6. USB cable (touch): 300cm
B45: PMC-1500 Optional Base | C45: T Base | D45: 79050A5230000 Base Kit/A5-2/Black/W/O Logo/GP | E45: 30 | F45: Separate Packing with PMC-1500. 6pcs/Carton with MOQ 6pcs
B47: New PM-116-2 Display only | C47: New PM-116 without Base, - Bezel-Free - with Speaker - support both HDMI/VGA Packing includes VGA/ HDMI/ DC 12V | D47: 2614151116300 PM-116-II/Black/No Logo | E47: =120+5+10 -> 135
B48: New PM-116-2 with PCT Touch | C48: New PM-116 without Base, - Bezel-Free - with Speaker - support both HDMI/VGA Packing includes VGA/ HDMI/ DC 12V, USB Touch Cable | D48: 2614151116301 PM-116-II/PCT/Black/No Logo | E48: =145+5+10 -> 160
B49: Pole of PM-116 | C49: Pole Mount only of PM-116 | D49: 7905920010000 Pole/PM-116/GP | E49: 45
B50: CD-7220 | C50: CD-7220 BOE Tube without Stand | E50: 50
B52: CD-101 | C52: CD-101C+JSTCableOnly/9cm/ NOLogo/Black/1.1/G+ | D52: 2614151101313 | E52: 109 | F52: *MOQ 240pcs
B53: CD-101 | C53: CD-101C+JSTCableOnly/9cm/ PTU/NOLogo/Black/1.1/GP | D53: 2614551101303 | E53: 109 | F53: *MOQ 240pcs, PTU P/N, same as 2614151101313
B54: CD-101 | C54: CD-101C+JSTCableOnly/9cm/NO Logo/White+Silver/1.1/G+ | D54: 2614151101315 | E54: 113 | F54: *MOQ 240pcs, While & Silver version of 2614151101313
B55: CD-101 | C55: CD-101C+JSTCableOnly/9cm/ PTU/NOLogo/Silver/1.1/GP | D55: 2614551101302 | E55: 113 | F55: *MOQ 240pcs, Silver version of 2614551101303
B56: CD-101 | C56: CD-101C+JSTCableOnly/9cm/1.1 /PTU/NOLogo/White+Silver/GP | D56: 2614551101308 | E56: 113 | F56: *MOQ 240pcs, White & Silver version of 2614551101303
B57: CD-101 | C57: CD-101C+JSTCableOnly/PCT/ 9cm/NOLogo/Black/1.1/G+ | D57: 2614151101314 | E57: 134 | F57: *MOQ 240pcs
B58: CD-101 | C58: CD-101C+JSTCableOnly/PCT/9cm /1.1/PTU/NOLogo/Black/GP | D58: 2614551101305 | E58: 134 | F58: *MOQ 240pcs, PTU P/N, same as 2614151101314
B59: CD-101 | C59: CD-101C+JST Cable Only/PCT/9cm/NO Logo/White+Silver/1.1/G+ | D59: 2614151101316 | E59: 138 | F59: *MOQ 240pcs, While & Silver version of 2614151101314
B60: CD-101 | C60: CD-101C+JSTCableOnly/PCT/9cm/ PTU/NOLogo/White+Silver/1.1/GP | D60: 2614551101309 | E60: 138 | F60: *MOQ 240pcs, While & Silver version of 2614551101305
B61: CD-101 | C61: CD-101C+JSTCableOnly/PCT/9cm /PTU/NOLogo/Silver/1.1/GP | D61: 2614551101304 | E61: 138 | F61: *MOQ 240pcs, Silver version of 2614551101305
B62: CD-101 FHD | C62: CD-101C FHD w/o touch | D62: TBD | E62: 150 | F62: *MOQ 240pcs
B63: CD-101 FHD | C63: CD-101C FHD w/ touch | D63: 2614151101312 | E63: 175 | F63: *MOQ 240pcs
B65: Coco | C65: Coco without Touch | D65: 26147C0C01000 | E65: 120
B66: Coco | C66: Coco with Touch | D66: 26147C0C01100 | E66: 145
B67: Coco | C67: Coco with Touch + RFID | D67: 79059C0C003N0 | E67: 185 | F67: *Changed to 790 P/N
B68: Coco - Made in Taiwan | C68: COCO 10.1"+JST6P/16:9 FHD/USB 2.0/DC5V/PTU/Black/Partner Logo | D68: 79059C0C00000 | E68: 130 | F68: PTU Only
B69: Coco - Made in Taiwan | C69: COCO 10.1"+JST6P/16:9 FHD/PCT/USB 2.0/DC5V/PTU/Black/Partner Logo | D69: 79059C0C00100 | E69: 155 | F69: PTU Only
B70: Coco - Made in Taiwan | C70: COCO 10.1"+JST6P/16:9 FHD/PCT/RF551V/USB 2.0/DC5V/PTU/Black/Partner Logo/GP | D70: 79059C0C003N2 | E70: 195 | F70: PTU Only
B71: Coco | C71: RFID | D71: 79059C0C09100 | E71: 45
B72: Coco | C72: Payment VP3350 housing | D72: 261493C0C0000 | E72: 7
B73: Coco | C73: Plastic Stand | D73: 261490C0C0000 | E73: 5
B74: Coco | C74: Magnetic stand | D74: 261490C0C0002 | E74: 20 | F74: Changed P/N for better cable management
B100: CD-101 | C100: CD-101C+JSTCableOnly/PCT/ 9cm/NOLogo/Black/1.1/G+ | D100: 2614151101314 | E100: 88
B101: CD-101 | C101: CD-101C+JSTCableOnly/PCT/9cm /1.1/PTU/NOLogo/Black/GP | D101: 2614551101305 | E101: 88
